Workbook

Sheet Leia-me
A1: CRM em quadro · Contorno Estética
A2: Clínica fictícia criada para o IA Sem Segredo. Nomes e números são inventados.
A4: Para que serve | B4: Organizar cada cliente numa etapa do funil e mostrar, todo dia, quem precisa de retorno.
A5: Clientes | B5: A base do CRM. As 80 clientes da planilha antiga já estão aqui, cada uma na etapa certa. Uma linha = um cartão do quadro.
A6: Painel | B6: Os números para a Paula: quantas clientes em cada etapa, retornos atrasados, origem e propostas que viraram pacote.
A7: Etapas do funil | B7: As 8 colunas do quadro, quando o cartão entra em cada uma e quem move.
A8: Dados do cliente | B8: O que cada campo significa e como preencher.
A9: Regras de retorno | B9: Quando a Nina volta a falar com a cliente em cada situação.
A10: Regras da clínica | B10: As regras que ninguém quebra e o que o CRM faz para proteger cada uma.
A11: Quem usa | B11: O que Nina, Otávio, Camila e Paula fazem no CRM.
A12: Pontos a confirmar | B12: Regras sugeridas que a Paula ainda precisa aprovar.
A14: COMO USAR NO DIA A DIA
A15: 1. | B15: Abra a aba Clientes e filtre a coluna "Situação do retorno" por "Atrasado" e "Hoje". Essa é a lista de retornos do dia.
A16: 2. | B16: Depois de falar com a cliente, atualize "Último contato" com a data de hoje e, se for o caso, mude a "Etapa".
A17: 3. | B17: Se a cliente não respondeu, some 1 em "Tentativas sem resposta". Na 3ª, a planilha avisa para mover para Perdido.
A18: 4. | B18: Se ela respondeu, volte as tentativas para 0.
A20: O QUE PREENCHER | B20: Células com fundo amarelo-claro são para preencher. As colunas "Área", "Validade do pacote", "Próximo retorno" e "Situação do retorno" são calculadas sozinhas: não digite nelas.
A21: MENUS | B21: Etapa, Origem, Interesse, Etiqueta da proposta, Responsável e Motivo da perda têm uma setinha com as opções. Escolha uma opção da lista em vez de escrever.
A22: DATAS | B22: As datas da planilha antiga não tinham ano. Considerei 2026 em todas.
A23: A COMPLETAR | B23: Clientes sem origem ou sem interesse na planilha antiga aparecem como "A completar". A Nina completa na próxima conversa.
A24: DOMINGO | B24: Se o próximo retorno cair num domingo, a planilha passa para segunda. Feriados precisam ser ajustados à mão.

Sheet Painel
A1: Painel da Paula
A2: Atualiza sozinho a partir da aba Clientes.
A4: Clientes por etapa | B4: Quantidade | D4: Retornos | E4: Quantidade
A5: Novo contato | B5: =COUNTIF(Clientes!$G$2:$G$500,A5) -> 8 | D5: Atrasado | E5: =COUNTIF(Clientes!$R$2:$R$500,D5) -> 52
A6: Em conversa | B6: =COUNTIF(Clientes!$G$2:$G$500,A6) -> 28 | D6: Hoje | E6: =COUNTIF(Clientes!$R$2:$R$500,D6) -> 27
A7: Avaliação marcada | B7: =COUNTIF(Clientes!$G$2:$G$500,A7) -> 18 | D7: Mover para Perdido | E7: =COUNTIF(Clientes!$R$2:$R$500,D7) -> 0
A8: Proposta enviada | B8: =COUNTIF(Clientes!$G$2:$G$500,A8) -> 18 | D8: No prazo | E8: =COUNTIF(Clientes!$R$2:$R$500,D8) -> 1
A9: Fechou pacote | B9: =COUNTIF(Clientes!$G$2:$G$500,A9) -> 8
A10: Em tratamento | B10: =COUNTIF(Clientes!$G$2:$G$500,A10) -> 0
A11: Pós-venda | B11: =COUNTIF(Clientes!$G$2:$G$500,A11) -> 0 | D11: Origem das clientes | E11: Quantidade
A12: Perdido | B12: =COUNTIF(Clientes!$G$2:$G$500,A12) -> 0 | D12: Instagram | E12: =COUNTIF(Clientes!$C$2:$C$500,D12) -> 30
A13: Total | B13: =SUM(B5:B12) -> 80 | D13: Instagram (anúncio) | E13: =COUNTIF(Clientes!$C$2:$C$500,D13) -> 11
D14: Google | E14: =COUNTIF(Clientes!$C$2:$C$500,D14) -> 5
A15: Propostas que viraram pacote | D15: Indicação | E15: =COUNTIF(Clientes!$C$2:$C$500,D15) -> 26
A16: Fecharam (Fechou pacote + Em tratamento + Pós-venda) | B16: =B9+B10+B11 -> 8 | D16: Fachada | E16: =COUNTIF(Clientes!$C$2:$C$500,D16) -> 0
A17: Ainda com proposta em aberto | B17: =B8 -> 18 | D17: Outro | E17: =COUNTIF(Clientes!$C$2:$C$500,D17) -> 0
A18: Taxa de fechamento | B18: =IF(B16+B17=0,0,B16/(B16+B17)) -> 0.30769231 | D18: A completar | E18: =COUNTIF(Clientes!$C$2:$C$500,D18) -> 8
A19: Referência da clínica: 4 em cada 10 avaliações viram pacote (média dos últimos 6 meses, documento Quem Somos).
A20: Fecharam ÷ (fecharam + propostas em aberto). Não conta as perdidas, porque a planilha antiga não dizia em que etapa a cliente desistiu.

Sheet Clientes
A1: Nome | B1: Telefone / WhatsApp | C1: Origem | D1: Indicada por | E1: Interesse | F1: Área | G1: Etapa | H1: Etiqueta da proposta | I1: Responsável | J1: Último contato | K1: Tentativas sem resposta | L1: Data da avaliação | M1: Data da 1ª sessão | N1: Sessões contratadas | O1: Sessões feitas | P1: Validade do pacote | Q1: Próximo retorno | R1: Situação do retorno | S1: Preferências e cuidados | T1: Motivo da perda | U1: Observação | V1: Situação na planilha antiga | W1: Retorno (cálculo)
A2: Cliente 001 | B2: (15) 99999-3042 | C2: Indicação | E2: Criolipólise | F2: =IF(OR(E2="",E2="A completar",E2="Ainda não sabe"),"",IF(OR(E2="Limpeza de pele",E2="Peeling de diamante",E2="Microagulhamento"),"Rosto","Corpo")) -> Corpo | G2: Avaliação marcada | I2: Nina | J2: 46256 | K2: 0 | P2: =IF(M2="","",EDATE(M2,6)) | Q2: =IF(W2="","",IF(WEEKDAY(W2)=1,W2+1,W2)) -> 46309 | R2: =IF(Q2="","",IF(AND(N(K2)>=3,G2<>"Perdido"),"Mover para Perdido",IF(Q2<TODAY(),"Atrasado",IF(Q2=TODAY(),"Hoje","No prazo")))) -> Hoje | V2: marcou avaliação | W2: =IF(G2="","",IF(OR(G2="Novo contato",G2="Em conversa"),IF(J2="",TODAY(),J2+1),IF(G2="Avaliação marcada",IF(L2="",TODAY(),L2-1),IF(G2="Proposta enviada",IF(J2="",TODAY(),J2+2),IF(G2="Fechou pacote",IF(J2="",TODAY(),J2+7),IF(G2="Em tratamento",IF(M2="",TODAY(),IF(TODAY()<=M2+1,M2+1,EDATE(M2,6)-30)),IF(G2="Pós-venda",IF(J2="",TODAY(),J2+7),IF(G2="Perdido",IF(J2="",TODAY(),J2+60),"")))))))) -> 46309
A3: Cliente 002 | B3: (15) 99999-3504 | C3: Indicação | E3: Drenagem linfática | F3: =IF(OR(E3="",E3="A completar",E3="Ainda não sabe"),"",IF(OR(E3="Limpeza de pele",E3="Peeling de diamante",E3="Microagulhamento"),"Rosto","Corpo")) -> Corpo | G3: Em conversa | I3: Nina | K3: 1 | P3: =IF(M3="","",EDATE(M3,6)) | Q3: =IF(W3="","",IF(WEEKDAY(W3)=1,W3+1,W3)) -> 46309 | R3: =IF(Q3="","",IF(AND(N(K3)>=3,G3<>"Perdido"),"Mover para Perdido",IF(Q3<TODAY(),"Atrasado",IF(Q3=TODAY(),"Hoje","No prazo")))) -> Hoje | V3: sumiu | W3: =IF(G3="","",IF(OR(G3="Novo contato",G3="Em conversa"),IF(J3="",TODAY(),J3+1),IF(G3="Avaliação marcada",IF(L3="",TODAY(),L3-1),IF(G3="Proposta enviada",IF(J3="",TODAY(),J3+2),IF(G3="Fechou pacote",IF(J3="",TODAY(),J3+7),IF(G3="Em tratamento",IF(M3="",TODAY(),IF(TODAY()<=M3+1,M3+1,EDATE(M3,6)-30)),IF(G3="Pós-venda",IF(J3="",TODAY(),J3+7),IF(G3="Perdido",IF(J3="",TODAY(),J3+60),"")))))))) -> 46309
A4: Cliente 003 | B4: (15) 99999-4519 | C4: Instagram | E4: Limpeza de pele | F4: =IF(OR(E4="",E4="A completar",E4="Ainda não sabe"),"",IF(OR(E4="Limpeza de pele",E4="Peeling de diamante",E4="Microagulhamento"),"Rosto","Corpo")) -> Rosto | G4: Proposta enviada | I4: Nina | J4: 46300 | K4: 0 | P4: =IF(M4="","",EDATE(M4,6)) | Q4: =IF(W4="","",IF(WEEKDAY(W4)=1,W4+1,W4)) -> 46302 | R4: =IF(Q4="","",IF(AND(N(K4)>=3,G4<>"Perdido"),"Mover para Perdido",IF(Q4<TODAY(),"Atrasado",IF(Q4=TODAY(),"Hoje","No prazo")))) -> Atrasado | S4: Já fez em outra clínica | V4: fez avaliação | W4: =IF(G4="","",IF(OR(G4="Novo contato",G4="Em conversa"),IF(J4="",TODAY(),J4+1),IF(G4="Avaliação marcada",IF(L4="",TODAY(),L4-1),IF(G4="Proposta enviada",IF(J4="",TODAY(),J4+2),IF(G4="Fechou pacote",IF(J4="",TODAY(),J4+7),IF(G4="Em tratamento",IF(M4="",TODAY(),IF(TODAY()<=M4+1,M4+1,EDATE(M4,6)-30)),IF(G4="Pós-venda",IF(J4="",TODAY(),J4+7),IF(G4="Perdido",IF(J4="",TODAY(),J4+60),"")))))))) -> 46302
A5: Cliente 004 | B5: (15) 99999-4205 | C5: Google | E5: Depilação a laser | F5: =IF(OR(E5="",E5="A completar",E5="Ainda não sabe"),"",IF(OR(E5="Limpeza de pele",E5="Peeling de diamante",E5="Microagulhamento"),"Rosto","Corpo")) -> Corpo | G5: Em conversa | I5: Nina | J5: 46278 | K5: 1 | P5: =IF(M5="","",EDATE(M5,6)) | Q5: =IF(W5="","",IF(WEEKDAY(W5)=1,W5+1,W5)) -> 46279 | R5: =IF(Q5="","",IF(AND(N(K5)>=3,G5<>"Perdido"),"Mover para Perdido",IF(Q5<TODAY(),"Atrasado",IF(Q5=TODAY(),"Hoje","No prazo")))) -> Atrasado | S5: Pediu foto de antes e depois: só com autorização escrita | V5: não respondeu | W5: =IF(G5="","",IF(OR(G5="Novo contato",G5="Em conversa"),IF(J5="",TODAY(),J5+1),IF(G5="Avaliação marcada",IF(L5="",TODAY(),L5-1),IF(G5="Proposta enviada",IF(J5="",TODAY(),J5+2),IF(G5="Fechou pacote",IF(J5="",TODAY(),J5+7),IF(G5="Em tratamento",IF(M5="",TODAY(),IF(TODAY()<=M5+1,M5+1,EDATE(M5,6)-30)),IF(G5="Pós-venda",IF(J5="",TODAY(),J5+7),IF(G5="Perdido",IF(J5="",TODAY(),J5+60),"")))))))) -> 46279
A6: Cliente 005 | B6: (15) 99999-5967 | C6: A completar | E6: Peeling de diamante | F6: =IF(OR(E6="",E6="A completar",E6="Ainda não sabe"),"",IF(OR(E6="Limpeza de pele",E6="Peeling de diamante",E6="Microagulhamento"),"Rosto","Corpo")) -> Rosto | G6: Proposta enviada | H6: achou caro | I6: Nina | J6: 46295 | K6: 0 | P6: =IF(M6="","",EDATE(M6,6)) | Q6: =IF(W6="","",IF(WEEKDAY(W6)=1,W6+1,W6)) -> 46297 | R6: =IF(Q6="","",IF(AND(N(K6)>=3,G6<>"Perdido"),"Mover para Perdido",IF(Q6<TODAY(),"Atrasado",IF(Q6=TODAY(),"Hoje","No prazo")))) -> Atrasado | V6: achou caro | W6: =IF(G6="","",IF(OR(G6="Novo contato",G6="Em conversa"),IF(J6="",TODAY(),J6+1),IF(G6="Avaliação marcada",IF(L6="",TODAY(),L6-1),IF(G6="Proposta enviada",IF(J6="",TODAY(),J6+2),IF(G6="Fechou pacote",IF(J6="",TODAY(),J6+7),IF(G6="Em tratamento",IF(M6="",TODAY(),IF(TODAY()<=M6+1,M6+1,EDATE(M6,6)-30)),IF(G6="Pós-venda",IF(J6="",TODAY(),J6+7),IF(G6="Perdido",IF(J6="",TODAY(),J6+60),"")))))))) -> 46297
A7: Cliente 006 | B7: (15) 99999-4307 | C7: Instagram (anúncio) | E7: Criolipólise | F7: =IF(OR(E7="",E7="A completar",E7="Ainda não sabe"),"",IF(OR(E7="Limpeza de pele",E7="Peeling de diamante",E7="Microagulhamento"),"Rosto","Corpo")) -> Corpo | G7: Em conversa | I7: Nina | J7: 46267 | K7: 1 | P7: =IF(M7="","",EDATE(M7,6)) | Q7: =IF(W7="","",IF(WEEKDAY(W7)=1,W7+1,W7)) -> 46268 | R7: =IF(Q7="","",IF(AND(N(K7)>=3,G7<>"Perdido"),"Mover para Perdido",IF(Q7<TODAY(),"Atrasado",IF(Q7=TODAY(),"Hoje","No prazo")))) -> Atrasado | S7: Já fez em outra clínica | V7: não respondeu | W7: =IF(G7="","",IF(OR(G7="Novo contato",G7="Em conversa"),IF(J7="",TODAY(),J7+1),IF(G7="Avaliação marcada",IF(L7="",TODAY(),L7-1),IF(G7="Proposta enviada",IF(J7="",TODAY(),J7+2),IF(G7="Fechou pacote",IF(J7="",TODAY(),J7+7),IF(G7="Em tratamento",IF(M7="",TODAY(),IF(TODAY()<=M7+1,M7+1,EDATE(M7,6)-30)),IF(G7="Pós-venda",IF(J7="",TODAY(),J7+7),IF(G7="Perdido",IF(J7="",TODAY(),J7+60),"")))))))) -> 46268
A8: Cliente 007 | B8: (15) 99999-3319 | C8: Instagram | E8: Peeling de diamante | F8: =IF(OR(E8="",E8="A completar",E8="Ainda não sabe"),"",IF(OR(E8="Limpeza de pele",E8="Peeling de diamante",E8="Microagulhamento"),"Rosto","Corpo")) -> Rosto | G8: Proposta enviada | I8: Nina | J8: 46291 | K8: 0 | P8: =IF(M8="","",EDATE(M8,6)) | Q8: =IF(W8="","",IF(WEEKDAY(W8)=1,W8+1,W8)) -> 46293 | R8: =IF(Q8="","",IF(AND(N(K8)>=3,G8<>"Perdido"),"Mover para Perdido",IF(Q8<TODAY(),"Atrasado",IF(Q8=TODAY(),"Hoje","No prazo")))) -> Atrasado | S8: Só pode sábado | V8: fez avaliação | W8: =IF(G8="","",IF(OR(G8="Novo contato",G8="Em conversa"),IF(J8="",TODAY(),J8+1),IF(G8="Avaliação marcada",IF(L8="",TODAY(),L8-1),IF(G8="Proposta enviada",IF(J8="",TODAY(),J8+2),IF(G8="Fechou pacote",IF(J8="",TODAY(),J8+7),IF(G8="Em tratamento",IF(M8="",TODAY(),IF(TODAY()<=M8+1,M8+1,EDATE(M8,6)-30)),IF(G8="Pós-venda",IF(J8="",TODAY(),J8+7),IF(G8="Perdido",IF(J8="",TODAY(),J8+60),"")))))))) -> 46293
A9: Cliente 008 | B9: (15) 99999-4589 | C9: A completar | E9: Criolipólise | F9: =IF(OR(E9="",E9="A completar",E9="Ainda não sabe"),"",IF(OR(E9="Limpeza de pele",E9="Peeling de diamante",E9="Microagulhamento"),"Rosto","Corpo")) -> Corpo | G9: Em conversa | I9: Nina | J9: 46281 | K9: 0 | P9: =IF(M9="","",EDATE(M9,6)) | Q9: =IF(W9="","",IF(WEEKDAY(W9)=1,W9+1,W9)) -> 46282 | R9: =IF(Q9="","",IF(AND(N(K9)>=3,G9<>"Perdido"),"Mover para Perdido",IF(Q9<TODAY(),"Atrasado",IF(Q9=TODAY(),"Hoje","No prazo")))) -> Atrasado | S9: Já fez em outra clínica | V9: ligar de novo | W9: =IF(G9="","",IF(OR(G9="Novo contato",G9="Em conversa"),IF(J9="",TODAY(),J9+1),IF(G9="Avaliação marcada",IF(L9="",TODAY(),L9-1),IF(G9="Proposta enviada",IF(J9="",TODAY(),J9+2),IF(G9="Fechou pacote",IF(J9="",TODAY(),J9+7),IF(G9="Em tratamento",IF(M9="",TODAY(),IF(TODAY()<=M9+1,M9+1,EDATE(M9,6)-30)),IF(G9="Pós-venda",IF(J9="",TODAY(),J9+7),IF(G9="Perdido",IF(J9="",TODAY(),J9+60),"")))))))) -> 46282
A10: Cliente 009 | B10: (15) 99999-3861 | C10: Indicação | E10: Peeling de diamante | F10: =IF(OR(E10="",E10="A completar",E10="Ainda não sabe"),"",IF(OR(E10="Limpeza de pele",E10="Peeling de diamante",E10="Microagulhamento"),"Rosto","Corpo")) -> Rosto | G10: Avaliação marcada | I10: Nina | J10: 46293 | K10: 0 | P10: =IF(M10="","",EDATE(M10,6)) | Q10: =IF(W10="","",IF(WEEKDAY(W10)=1,W10+1,W10)) -> 46309 | R10: =IF(Q10="","",IF(AND(N(K10)>=3,G10<>"Perdido"),"Mover para Perdido",IF(Q10<TODAY(),"Atrasado",IF(Q10=TODAY(),"Hoje","No prazo")))) -> Hoje | V10: avaliação? | W10: =IF(G10="","",IF(OR(G10="Novo contato",G10="Em conversa"),IF(J10="",TODAY(),J10+1),IF(G10="Avaliação marcada",IF(L10="",TODAY(),L10-1),IF(G10="Proposta enviada",IF(J10="",TODAY(),J10+2),IF(G10="Fechou pacote",IF(J10="",TODAY(),J10+7),IF(G10="Em tratamento",IF(M10="",TODAY(),IF(TODAY()<=M10+1,M10+1,EDATE(M10,6)-30)),IF(G10="Pós-venda",IF(J10="",TODAY(),J10+7),IF(G10="Perdido",IF(J10="",TODAY(),J10+60),"")))))))) -> 46309
A11: Cliente 010 | B11: (15) 99999-7596 | C11: A completar | E11: Drenagem linfática | F11: =IF(OR(E11="",E11="A completar",E11="Ainda não sabe"),"",IF(OR(E11="Limpeza de pele",E11="Peeling de diamante",E11="Microagulhamento"),"Rosto","Corpo")) -> Corpo | G11: Avaliação marcada | I11: Nina | J11: 46278 | K11: 0 | P11: =IF(M11="","",EDATE(M11,6)) | Q11: =IF(W11="","",IF(WEEKDAY(W11)=1,W11+1,W11)) -> 46309 | R11: =IF(Q11="","",IF(AND(N(K11)>=3,G11<>"Perdido"),"Mover para Perdido",IF(Q11<TODAY(),"Atrasado",IF(Q11=TODAY(),"Hoje","No prazo")))) -> Hoje | S11: Perguntou do resultado: nunca prometer cm ou kg | V11: remarcar | W11: =IF(G11="","",IF(OR(G11="Novo contato",G11="Em conversa"),IF(J11="",TODAY(),J11+1),IF(G11="Avaliação marcada",IF(L11="",TODAY(),L11-1),IF(G11="Proposta enviada",IF(J11="",TODAY(),J11+2),IF(G11="Fechou pacote",IF(J11="",TODAY(),J11+7),IF(G11="Em tratamento",IF(M11="",TODAY(),IF(TODAY()<=M11+1,M11+1,EDATE(M11,6)-30)),IF(G11="Pós-venda",IF(J11="",TODAY(),J11+7),IF(G11="Perdido",IF(J11="",TODAY(),J11+60),"")))))))) -> 46309
A12: Cliente 011 | B12: (15) 99999-8159 | C12: Instagram (anúncio) | E12: Massagem modeladora | F12: =IF(OR(E12="",E12="A completar",E12="Ainda não sabe"),"",IF(OR(E12="Limpeza de pele",E12="Peeling de diamante",E12="Microagulhamento"),"Rosto","Corpo")) -> Corpo | G12: Avaliação marcada | I12: Nina | J12: 46228 | K12: 0 | P12: =IF(M12="","",EDATE(M12,6)) | Q12: =IF(W12="","",IF(WEEKDAY(W12)=1,W12+1,W12)) -> 46309 | R12: =IF(Q12="","",IF(AND(N(K12)>=3,G12<>"Perdido"),"Mover para Perdido",IF(Q12<TODAY(),"Atrasado",IF(Q12=TODAY(),"Hoje","No prazo")))) -> Hoje | S12: Perguntou do resultado: nunca prometer cm ou kg | V12: avaliação? | W12: =IF(G12="","",IF(OR(G12="Novo contato",G12="Em conversa"),IF(J12="",TODAY(),J12+1),IF(G12="Avaliação marcada",IF(L12="",TODAY(),L12-1),IF(G12="Proposta enviada",IF(J12="",TODAY(),J12+2),IF(G12="Fechou pacote",IF(J12="",TODAY(),J12+7),IF(G12="Em tratamento",IF(M12="",TODAY(),IF(TODAY()<=M12+1,M12+1,EDATE(M12,6)-30)),IF(G12="Pós-venda",IF(J12="",TODAY(),J12+7),IF(G12="Perdido",IF(J12="",TODAY(),J12+60),"")))))))) -> 46309
A13: Cliente 012 | B13: (15) 99999-5744 | C13: Indicação | E13: Peeling de diamante | F13: =IF(OR(E13="",E13="A completar",E13="Ainda não sabe"),"",IF(OR(E13="Limpeza de pele",E13="Peeling de diamante",E13="Microagulhamento"),"Rosto","Corpo")) -> Rosto | G13: Novo contato | I13: Nina | J13: 46255 | K13: 0 | P13: =IF(M13="","",EDATE(M13,6)) | Q13: =IF(W13="","",IF(WEEKDAY(W13)=1,W13+1,W13)) -> 46256 | R13: =IF(Q13="","",IF(AND(N(K13)>=3,G13<>"Perdido"),"Mover para Perdido",IF(Q13<TODAY(),"Atrasado",IF(Q13=TODAY(),"Hoje","No prazo")))) -> Atrasado | V13: (em branco) | W13: =IF(G13="","",IF(OR(G13="Novo contato",G13="Em conversa"),IF(J13="",TODAY(),J13+1),IF(G13="Avaliação marcada",IF(L13="",TODAY(),L13-1),IF(G13="Proposta enviada",IF(J13="",TODAY(),J13+2),IF(G13="Fechou pacote",IF(J13="",TODAY(),J13+7),IF(G13="Em tratamento",IF(M13="",TODAY(),IF(TODAY()<=M13+1,M13+1,EDATE(M13,6)-30)),IF(G13="Pós-venda",IF(J13="",TODAY(),J13+7),IF(G13="Perdido",IF(J13="",TODAY(),J13+60),"")))))))) -> 46256
A14: Cliente 013 | B14: (15) 99999-8132 | C14: Indicação | E14: Drenagem linfática | F14: =IF(OR(E14="",E14="A completar",E14="Ainda não sabe"),"",IF(OR(E14="Limpeza de pele",E14="Peeling de diamante",E14="Microagulhamento"),"Rosto","Corpo")) -> Corpo | G14: Em conversa | I14: Nina | J14: 46300 | K14: 0 | P14: =IF(M14="","",EDATE(M14,6)) | Q14: =IF(W14="","",IF(WEEKDAY(W14)=1,W14+1,W14)) -> 46301 | R14: =IF(Q14="","",IF(AND(N(K14)>=3,G14<>"Perdido"),"Mover para Perdido",IF(Q14<TODAY(),"Atrasado",IF(Q14=TODAY(),"Hoje","No prazo")))) -> Atrasado | S14: Prefere áudio | V14: ligar de novo | W14: =IF(G14="","",IF(OR(G14="Novo contato",G14="Em conversa"),IF(J14="",TODAY(),J14+1),IF(G14="Avaliação marcada",IF(L14="",TODAY(),L14-1),IF(G14="Proposta enviada",IF(J14="",TODAY(),J14+2),IF(G14="Fechou pacote",IF(J14="",TODAY(),J14+7),IF(G14="Em tratamento",IF(M14="",TODAY(),IF(TODAY()<=M14+1,M14+1,EDATE(M14,6)-30)),IF(G14="Pós-venda",IF(J14="",TODAY(),J14+7),IF(G14="Perdido",IF(J14="",TODAY(),J14+60),"")))))))) -> 46301
A15: Cliente 014 | B15: (15) 99999-9337 | C15: Indicação | D15: Amiga (confirmar nome) | E15: Criolipólise | F15: =IF(OR(E15="",E15="A completar",E15="Ainda não sabe"),"",IF(OR(E15="Limpeza de pele",E15="Peeling de diamante",E15="Microagulhamento"),"Rosto","Corpo")) -> Corpo | G15: Proposta enviada | I15: Nina | J15: 46227 | K15: 0 | P15: =IF(M15="","",EDATE(M15,6)) | Q15: =IF(W15="","",IF(WEEKDAY(W15)=1,W15+1,W15)) -> 46230 | R15: =IF(Q15="","",IF(AND(N(K15)>=3,G15<>"Perdido"),"Mover para Perdido",IF(Q15<TODAY(),"Atrasado",IF(Q15=TODAY(),"Hoje","No prazo")))) -> Atrasado | U15: Na planilha antiga a origem era Google, mas a cliente veio pela amiga. | V15: fez avaliação | W15: =IF(G15="","",IF(OR(G15="Novo contato",G15="Em conversa"),IF(J15="",TODAY(),J15+1),IF(G15="Avaliação marcada",IF(L15="",TODAY(),L15-1),IF(G15="Proposta enviada",IF(J15="",TODAY(),J15+2),IF(G15="Fechou pacote",IF(J15="",TODAY(),J15+7),IF(G15="Em tratamento",IF(M15="",TODAY(),IF(TODAY()<=M15+1,M15+1,EDATE(M15,6)-30)),IF(G15="Pós-venda",IF(J15="",TODAY(),J15+7),IF(G15="Perdido",IF(J15="",TODAY(),J15+60),"")))))))) -> 46229
A16: Cliente 015 | B16: (15) 99999-9097 | C16: Instagram | E16: Depilação a laser | F16: =IF(OR(E16="",E16="A completar",E16="Ainda não sabe"),"",IF(OR(E16="Limpeza de pele",E16="Peeling de diamante",E16="Microagulhamento"),"Rosto","Corpo")) -> Corpo | G16: Avaliação marcada | I16: Nina | J16: 46244 | K16: 0 | P16: =IF(M16="","",EDATE(M16,6)) | Q16: =IF(W16="","",IF(WEEKDAY(W16)=1,W16+1,W16)) -> 46309 | R16: =IF(Q16="","",IF(AND(N(K16)>=3,G16<>"Perdido"),"Mover para Perdido",IF(Q16<TODAY(),"Atrasado",IF(Q16=TODAY(),"Hoje","No prazo")))) -> Hoje | V16: avaliação? | W16: =IF(G16="","",IF(OR(G16="Novo contato",G16="Em conversa"),IF(J16="",TODAY(),J16+1),IF(G16="Avaliação marcada",IF(L16="",TODAY(),L16-1),IF(G16="Proposta enviada",IF(J16="",TODAY(),J16+2),IF(G16="Fechou pacote",IF(J16="",TODAY(),J16+7),IF(G16="Em tratamento",IF(M16="",TODAY(),IF(TODAY()<=M16+1,M16+1,EDATE(M16,6)-30)),IF(G16="Pós-venda",IF(J16="",TODAY(),J16+7),IF(G16="Perdido",IF(J16="",TODAY(),J16+60),"")))))))) -> 46309
A17: Cliente 016 | B17: (15) 99999-9112 | C17: Instagram | E17: A completar | F17: =IF(OR(E17="",E17="A completar",E17="Ainda não sabe"),"",IF(OR(E17="Limpeza de pele",E17="Peeling de diamante",E17="Microagulhamento"),"Rosto","Corpo")) | G17: Fechou pacote | I17: Nina | J17: 46277 | K17: 0 | P17: =IF(M17="","",EDATE(M17,6)) | Q17: =IF(W17="","",IF(WEEKDAY(W17)=1,W17+1,W17)) -> 46284 | R17: =IF(Q17="","",IF(AND(N(K17)>=3,G17<>"Perdido"),"Mover para Perdido",IF(Q17<TODAY(),"Atrasado",IF(Q17=TODAY(),"Hoje","No prazo")))) -> Atrasado | V17: fechou pacote | W17: =IF(G17="","",IF(OR(G17="Novo contato",G17="Em conversa"),IF(J17="",TODAY(),J17+1),IF(G17="Avaliação marcada",IF(L17="",TODAY(),L17-1),IF(G17="Proposta enviada",IF(J17="",TODAY(),J17+2),IF(G17="Fechou pacote",IF(J17="",TODAY(),J17+7),IF(G17="Em tratamento",IF(M17="",TODAY(),IF(TODAY()<=M17+1,M17+1,EDATE(M17,6)-30)),IF(G17="Pós-venda",IF(J17="",TODAY(),J17+7),IF(G17="Perdido",IF(J17="",TODAY(),J17+60),"")))))))) -> 46284
A18: Cliente 017 | B18: (15) 99999-5088 | C18: Instagram | E18: Microagulhamento | F18: =IF(OR(E18="",E18="A completar",E18="Ainda não sabe"),"",IF(OR(E18="Limpeza de pele",E18="Peeling de diamante",E18="Microagulhamento"),"Rosto","Corpo")) -> Rosto | G18: Proposta enviada | H18: quer parcelar | I18: Nina | K18: 0 | P18: =IF(M18="","",EDATE(M18,6)) | Q18: =IF(W18="","",IF(WEEKDAY(W18)=1,W18+1,W18)) -> 46309 | R18: =IF(Q18="","",IF(AND(N(K18)>=3,G18<>"Perdido"),"Mover para Perdido",IF(Q18<TODAY(),"Atrasado",IF(Q18=TODAY(),"Hoje","No prazo")))) -> Hoje | S18: Quer parcelar | V18: fez avaliação | W18: =IF(G18="","",IF(OR(G18="Novo contato",G18="Em conversa"),IF(J18="",TODAY(),J18+1),IF(G18="Avaliação marcada",IF(L18="",TODAY(),L18-1),IF(G18="Proposta enviada",IF(J18="",TODAY(),J18+2),IF(G18="Fechou pacote",IF(J18="",TODAY(),J18+7),IF(G18="Em tratamento",IF(M18="",TODAY(),IF(TODAY()<=M18+1,M18+1,EDATE(M18,6)-30)),IF(G18="Pós-venda",IF(J18="",TODAY(),J18+7),IF(G18="Perdido",IF(J18="",TODAY(),J18+60),"")))))))) -> 46309
A19: Cliente 018 | B19: (15) 99999-1268 | C19: Instagram (anúncio) | E19: Peeling de diamante | F19: =IF(OR(E19="",E19="A completar",E19="Ainda não sabe"),"",IF(OR(E19="Limpeza de pele",E19="Peeling de diamante",E19="Microagulhamento"),"Rosto","Corpo")) -> Rosto | G19: Em conversa | I19: Nina | J19: 46295 | K19: 0 | P19: =IF(M19="","",EDATE(M19,6)) | Q19: =IF(W19="","",IF(WEEKDAY(W19)=1,W19+1,W19)) -> 46296 | R19: =IF(Q19="","",IF(AND(N(K19)>=3,G19<>"Perdido"),"Mover para Perdido",IF(Q19<TODAY(),"Atrasado",IF(Q19=TODAY(),"Hoje","No prazo")))) -> Atrasado | V19: pediu preço | W19: =IF(G19="","",IF(OR(G19="Novo contato",G19="Em conversa"),IF(J19="",TODAY(),J19+1),IF(G19="Avaliação marcada",IF(L19="",TODAY(),L19-1),IF(G19="Proposta enviada",IF(J19="",TODAY(),J19+2),IF(G19="Fechou pacote",IF(J19="",TODAY(),J19+7),IF(G19="Em tratamento",IF(M19="",TODAY(),IF(TODAY()<=M19+1,M19+1,EDATE(M19,6)-30)),IF(G19="Pós-venda",IF(J19="",TODAY(),J19+7),IF(G19="Perdido",IF(J19="",TODAY(),J19+60),"")))))))) -> 46296
A20: Cliente 019 | B20: (15) 99999-8135 | C20: Indicação | D20: Amiga (confirmar nome) | E20: Depilação a laser | F20: =IF(OR(E20="",E20="A completar",E20="Ainda não sabe"),"",IF(OR(E20="Limpeza de pele",E20="Peeling de diamante",E20="Microagulhamento"),"Rosto","Corpo")) -> Corpo | G20: Proposta enviada | H20: achou caro | I20: Nina | J20: 46263 | K20: 0 | P20: =IF(M20="","",EDATE(M20,6)) | Q20: =IF(W20="","",IF(WEEKDAY(W20)=1,W20+1,W20)) -> 46265 | R20: =IF(Q20="","",IF(AND(N(K20)>=3,G20<>"Perdido"),"Mover para Perdido",IF(Q20<TODAY(),"Atrasado",IF(Q20=TODAY(),"Hoje","No prazo")))) -> Atrasado | U20: Na planilha antiga a origem era Instagram (anúncio), mas a cliente veio pela amiga. | V20: achou caro | W20: =IF(G20="","",IF(OR(G20="Novo contato",G20="Em conversa"),IF(J20="",TODAY(),J20+1),IF(G20="Avaliação marcada",IF(L20="",TODAY(),L20-1),IF(G20="Proposta enviada",IF(J20="",TODAY(),J20+2),IF(G20="Fechou pacote",IF(J20="",TODAY(),J20+7),IF(G20="Em tratamento",IF(M20="",TODAY(),IF(TODAY()<=M20+1,M20+1,EDATE(M20,6)-30)),IF(G20="Pós-venda",IF(J20="",TODAY(),J20+7),IF(G20="Perdido",IF(J20="",TODAY(),J20+60),"")))))))) -> 46265
A21: Cliente 020 | B21: (15) 99999-6163 | C21: Instagram | E21: Criolipólise | F21: =IF(OR(E21="",E21="A completar",E21="Ainda não sabe"),"",IF(OR(E21="Limpeza de pele",E21="Peeling de diamante",E21="Microagulhamento"),"Rosto","Corpo")) -> Corpo | G21: Proposta enviada | I21: Nina | J21: 46260 | K21: 0 | P21: =IF(M21="","",EDATE(M21,6)) | Q21: =IF(W21="","",IF(WEEKDAY(W21)=1,W21+1,W21)) -> 46262 | R21: =IF(Q21="","",IF(AND(N(K21)>=3,G21<>"Perdido"),"Mover para Perdido",IF(Q21<TODAY(),"Atrasado",IF(Q21=TODAY(),"Hoje","No prazo")))) -> Atrasado | S21: Perguntou do resultado: nunca prometer cm ou kg | V21: fez avaliação | W21: =IF(G21="","",IF(OR(G21="Novo contato",G21="Em conversa"),IF(J21="",TODAY(),J21+1),IF(G21="Avaliação marcada",IF(L21="",TODAY(),L21-1),IF(G21="Proposta enviada",IF(J21="",TODAY(),J21+2),IF(G21="Fechou pacote",IF(J21="",TODAY(),J21+7),IF(G21="Em tratamento",IF(M21="",TODAY(),IF(TODAY()<=M21+1,M21+1,EDATE(M21,6)-30)),IF(G21="Pós-venda",IF(J21="",TODAY(),J21+7),IF(G21="Perdido",IF(J21="",TODAY(),J21+60),"")))))))) -> 46262
A22: Cliente 021 | B22: (15) 99999-9633 | C22: Indicação | E22: Peeling de diamante | F22: =IF(OR(E22="",E22="A completar",E22="Ainda não sabe"),"",IF(OR(E22="Limpeza de pele",E22="Peeling de diamante",E22="Microagulhamento"),"Rosto","Corpo")) -> Rosto | G22: Avaliação marcada | I22: Nina | J22: 46250 | K22: 0 | P22: =IF(M22="","",EDATE(M22,6)) | Q22: =IF(W22="","",IF(WEEKDAY(W22)=1,W22+1,W22)) -> 46309 | R22: =IF(Q22="","",IF(AND(N(K22)>=3,G22<>"Perdido"),"Mover para Perdido",IF(Q22<TODAY(),"Atrasado",IF(Q22=TODAY(),"Hoje","No prazo")))) -> Hoje | S22: Prefere áudio | V22: marcou avaliação | W22: =IF(G22="","",IF(OR(G22="Novo contato",G22="Em conversa"),IF(J22="",TODAY(),J22+1),IF(G22="Avaliação marcada",IF(L22="",TODAY(),L22-1),IF(G22="Proposta enviada",IF(J22="",TODAY(),J22+2),IF(G22="Fechou pacote",IF(J22="",TODAY(),J22+7),IF(G22="Em tratamento",IF(M22="",TODAY(),IF(TODAY()<=M22+1,M22+1,EDATE(M22,6)-30)),IF(G22="Pós-venda",IF(J22="",TODAY(),J22+7),IF(G22="Perdido",IF(J22="",TODAY(),J22+60),"")))))))) -> 46309
A23: Cliente 022 | B23: (15) 99999-5747 | C23: A completar | E23: Drenagem linfática | F23: =IF(OR(E23="",E23="A completar",E23="Ainda não sabe"),"",IF(OR(E23="Limpeza de pele",E23="Peeling de diamante",E23="Microagulhamento"),"Rosto","Corpo")) -> Corpo | G23: Fechou pacote | I23: Nina | J23: 46259 | K23: 0 | P23: =IF(M23="","",EDATE(M23,6)) | Q23: =IF(W23="","",IF(WEEKDAY(W23)=1,W23+1,W23)) -> 46266 | R23: =IF(Q23="","",IF(AND(N(K23)>=3,G23<>"Perdido"),"Mover para Perdido",IF(Q23<TODAY(),"Atrasado",IF(Q23=TODAY(),"Hoje","No prazo")))) -> Atrasado | S23: Perguntou do resultado: nunca prometer cm ou kg | V23: fechou pacote | W23: =IF(G23="","",IF(OR(G23="Novo contato",G23="Em conversa"),IF(J23="",TODAY(),J23+1),IF(G23="Avaliação marcada",IF(L23="",TODAY(),L23-1),IF(G23="Proposta enviada",IF(J23="",TODAY(),J23+2),IF(G23="Fechou pacote",IF(J23="",TODAY(),J23+7),IF(G23="Em tratamento",IF(M23="",TODAY(),IF(TODAY()<=M23+1,M23+1,EDATE(M23,6)-30)),IF(G23="Pós-venda",IF(J23="",TODAY(),J23+7),IF(G23="Perdido",IF(J23="",TODAY(),J23+60),"")))))))) -> 46266
A24: Cliente 023 | B24: (15) 99999-0747 | C24: Instagram | E24: Massagem modeladora | F24: =IF(OR(E24="",E24="A completar",E24="Ainda não sabe"),"",IF(OR(E24="Limpeza de pele",E24="Peeling de diamante",E24="Microagulhamento"),"Rosto","Corpo")) -> Corpo | G24: Avaliação marcada | I24: Nina | K24: 0 | P24: =IF(M24="","",EDATE(M24,6)) | Q24: =IF(W24="","",IF(WEEKDAY(W24)=1,W24+1,W24)) -> 46309 | R24: =IF(Q24="","",IF(AND(N(K24)>=3,G24<>"Perdido"),"Mover para Perdido",IF(Q24<TODAY(),"Atrasado",IF(Q24=TODAY(),"Hoje","No prazo")))) -> Hoje | S24: Já fez em outra clínica | V24: marcou avaliação | W24: =IF(G24="","",IF(OR(G24="Novo contato",G24="Em conversa"),IF(J24="",TODAY(),J24+1),IF(G24="Avaliação marcada",IF(L24="",TODAY(),L24-1),IF(G24="Proposta enviada",IF(J24="",TODAY(),J24+2),IF(G24="Fechou pacote",IF(J24="",TODAY(),J24+7),IF(G24="Em tratamento",IF(M24="",TODAY(),IF(TODAY()<=M24+1,M24+1,EDATE(M24,6)-30)),IF(G24="Pós-venda",IF(J24="",TODAY(),J24+7),IF(G24="Perdido",IF(J24="",TODAY(),J24+60),"")))))))) -> 46309
A25: Cliente 024 | B25: (15) 99999-6384 | C25: Google | E25: Drenagem linfática | F25: =IF(OR(E25="",E25="A completar",E25="Ainda não sabe"),"",IF(OR(E25="Limpeza de pele",E25="Peeling de diamante",E25="Microagulhamento"),"Rosto","Corpo")) -> Corpo | G25: Proposta enviada | I25: Nina | J25: 46284 | K25: 0 | P25: =IF(M25="","",EDATE(M25,6)) | Q25: =IF(W25="","",IF(WEEKDAY(W25)=1,W25+1,W25)) -> 46286 | R25: =IF(Q25="","",IF(AND(N(K25)>=3,G25<>"Perdido"),"Mover para Perdido",IF(Q25<TODAY(),"Atrasado",IF(Q25=TODAY(),"Hoje","No prazo")))) -> Atrasado | S25: Pediu foto de antes e depois: só com autorização escrita | V25: fez avaliação | W25: =IF(G25="","",IF(OR(G25="Novo contato",G25="Em conversa"),IF(J25="",TODAY(),J25+1),IF(G25="Avaliação marcada",IF(L25="",TODAY(),L25-1),IF(G25="Proposta enviada",IF(J25="",TODAY(),J25+2),IF(G25="Fechou pacote",IF(J25="",TODAY(),J25+7),IF(G25="Em tratamento",IF(M25="",TODAY(),IF(TODAY()<=M25+1,M25+1,EDATE(M25,6)-30)),IF(G25="Pós-venda",IF(J25="",TODAY(),J25+7),IF(G25="Perdido",IF(J25="",TODAY(),J25+60),"")))))))) -> 46286
A26: Cliente 025 | B26: (15) 99999-2430 | C26: Instagram | E26: Limpeza de pele | F26: =IF(OR(E26="",E26="A completar",E26="Ainda não sabe"),"",IF(OR(E26="Limpeza de pele",E26="Peeling de diamante",E26="Microagulhamento"),"Rosto","Corpo")) -> Rosto | G26: Fechou pacote | I26: Nina | J26: 46278 | K26: 0 | P26: =IF(M26="","",EDATE(M26,6)) | Q26: =IF(W26="","",IF(WEEKDAY(W26)=1,W26+1,W26)) -> 46286 | R26: =IF(Q26="","",IF(AND(N(K26)>=3,G26<>"Perdido"),"Mover para Perdido",IF(Q26<TODAY(),"Atrasado",IF(Q26=TODAY(),"Hoje","No prazo")))) -> Atrasado | V26: fechou pacote | W26: =IF(G26="","",IF(OR(G26="Novo contato",G26="Em conversa"),IF(J26="",TODAY(),J26+1),IF(G26="Avaliação marcada",IF(L26="",TODAY(),L26-1),IF(G26="Proposta enviada",IF(J26="",TODAY(),J26+2),IF(G26="Fechou pacote",IF(J26="",TODAY(),J26+7),IF(G26="Em tratamento",IF(M26="",TODAY(),IF(TODAY()<=M26+1,M26+1,EDATE(M26,6)-30)),IF(G26="Pós-venda",IF(J26="",TODAY(),J26+7),IF(G26="Perdido",IF(J26="",TODAY(),J26+60),"")))))))) -> 46285
A27: Cliente 026 | B27: (15) 99999-9883 | C27: A completar | E27: Massagem modeladora | F27: =IF(OR(E27="",E27="A completar",E27="Ainda não sabe"),"",IF(OR(E27="Limpeza de pele",E27="Peeling de diamante",E27="Microagulhamento"),"Rosto","Corpo")) -> Corpo | G27: Em conversa | I27: Nina | J27: 46250 | K27: 0 | P27: =IF(M27="","",EDATE(M27,6)) | Q27: =IF(W27="","",IF(WEEKDAY(W27)=1,W27+1,W27)) -> 46251 | R27: =IF(Q27="","",IF(AND(N(K27)>=3,G27<>"Perdido"),"Mover para Perdido",IF(Q27<TODAY(),"Atrasado",IF(Q27=TODAY(),"Hoje","No prazo")))) -> Atrasado | S27: Só pode sábado | V27: pediu preço | W27: =IF(G27="","",IF(OR(G27="Novo contato",G27="Em conversa"),IF(J27="",TODAY(),J27+1),IF(G27="Avaliação marcada",IF(L27="",TODAY(),L27-1),IF(G27="Proposta enviada",IF(J27="",TODAY(),J27+2),IF(G27="Fechou pacote",IF(J27="",TODAY(),J27+7),IF(G27="Em tratamento",IF(M27="",TODAY(),IF(TODAY()<=M27+1,M27+1,EDATE(M27,6)-30)),IF(G27="Pós-venda",IF(J27="",TODAY(),J27+7),IF(G27="Perdido",IF(J27="",TODAY(),J27+60),"")))))))) -> 46251
A28: Cliente 027 | B28: (15) 99999-8042 | C28: Instagram (anúncio) | E28: Microagulhamento | F28: =IF(OR(E28="",E28="A completar",E28="Ainda não sabe"),"",IF(OR(E28="Limpeza de pele",E28="Peeling de diamante",E28="Microagulhamento"),"Rosto","Corpo")) -> Rosto | G28: Em conversa | I28: Nina | K28: 0 | P28: =IF(M28="","",EDATE(M28,6)) | Q28: =IF(W28="","",IF(WEEKDAY(W28)=1,W28+1,W28)) -> 46309 | R28: =IF(Q28="","",IF(AND(N(K28)>=3,G28<>"Perdido"),"Mover para Perdido",IF(Q28<TODAY(),"Atrasado",IF(Q28=TODAY(),"Hoje","No prazo")))) -> Hoje | S28: Só pode sábado | V28: pediu preço | W28: =IF(G28="","",IF(OR(G28="Novo contato",G28="Em conversa"),IF(J28="",TODAY(),J28+1),IF(G28="Avaliação marcada",IF(L28="",TODAY(),L28-1),IF(G28="Proposta enviada",IF(J28="",TODAY(),J28+2),IF(G28="Fechou pacote",IF(J28="",TODAY(),J28+7),IF(G28="Em tratamento",IF(M28="",TODAY(),IF(TODAY()<=M28+1,M28+1,EDATE(M28,6)-30)),IF(G28="Pós-venda",IF(J28="",TODAY(),J28+7),IF(G28="Perdido",IF(J28="",TODAY(),J28+60),"")))))))) -> 46309
A29: Cliente 028 | B29: (15) 99999-0805 | C29: Google | E29: Criolipólise | F29: =IF(OR(E29="",E29="A completar",E29="Ainda não sabe"),"",IF(OR(E29="Limpeza de pele",E29="Peeling de diamante",E29="Microagulhamento"),"Rosto","Corpo")) -> Corpo | G29: Novo contato | I29: Nina | J29: 46291 | K29: 0 | P29: =IF(M29="","",EDATE(M29,6)) | Q29: =IF(W29="","",IF(WEEKDAY(W29)=1,W29+1,W29)) -> 46293 | R29: =IF(Q29="","",IF(AND(N(K29)>=3,G29<>"Perdido"),"Mover para Perdido",IF(Q29<TODAY(),"Atrasado",IF(Q29=TODAY(),"Hoje","No prazo")))) -> Atrasado | V29: (em branco) | W29: =IF(G29="","",IF(OR(G29="Novo contato",G29="Em conversa"),IF(J29="",TODAY(),J29+1),IF(G29="Avaliação marcada",IF(L29="",TODAY(),L29-1),IF(G29="Proposta enviada",IF(J29="",TODAY(),J29+2),IF(G29="Fechou pacote",IF(J29="",TODAY(),J29+7),IF(G29="Em tratamento",IF(M29="",TODAY(),IF(TODAY()<=M29+1,M29+1,EDATE(M29,6)-30)),IF(G29="Pós-venda",IF(J29="",TODAY(),J29+7),IF(G29="Perdido",IF(J29="",TODAY(),J29+60),"")))))))) -> 46292
A30: Cliente 029 | B30: (15) 99999-2453 | C30: Instagram | E30: A completar | F30: =IF(OR(E30="",E30="A completar",E30="Ainda não sabe"),"",IF(OR(E30="Limpeza de pele",E30="Peeling de diamante",E30="Microagulhamento"),"Rosto","Corpo")) | G30: Fechou pacote | I30: Nina | J30: 46223 | K30: 0 | P30: =IF(M30="","",EDATE(M30,6)) | Q30: =IF(W30="","",IF(WEEKDAY(W30)=1,W30+1,W30)) -> 46230 | R30: =IF(Q30="","",IF(AND(N(K30)>=3,G30<>"Perdido"),"Mover para Perdido",IF(Q30<TODAY(),"Atrasado",IF(Q30=TODAY(),"Hoje","No prazo")))) -> Atrasado | V30: fechou pacote | W30: =IF(G30="","",IF(OR(G30="Novo contato",G30="Em conversa"),IF(J30="",TODAY(),J30+1),IF(G30="Avaliação marcada",IF(L30="",TODAY(),L30-1),IF(G30="Proposta enviada",IF(J30="",TODAY(),J30+2),IF(G30="Fechou pacote",IF(J30="",TODAY(),J30+7),IF(G30="Em tratamento",IF(M30="",TODAY(),IF(TODAY()<=M30+1,M30+1,EDATE(M30,6)-30)),IF(G30="Pós-venda",IF(J30="",TODAY(),J30+7),IF(G30="Perdido",IF(J30="",TODAY(),J30+60),"")))))))) -> 46230
A31: Cliente 030 | B31: (15) 99999-3502 | C31: Indicação | D31: Amiga (confirmar nome) | E31: Depilação a laser | F31: =IF(OR(E31="",E31="A completar",E31="Ainda não sabe"),"",IF(OR(E31="Limpeza de pele",E31="Peeling de diamante",E31="Microagulhamento"),"Rosto","Corpo")) -> Corpo | G31: Proposta enviada | H31: achou caro | I31: Nina | J31: 46267 | K31: 0 | P31: =IF(M31="","",EDATE(M31,6)) | Q31: =IF(W31="","",IF(WEEKDAY(W31)=1,W31+1,W31)) -> 46269 | R31: =IF(Q31="","",IF(AND(N(K31)>=3,G31<>"Perdido"),"Mover para Perdido",IF(Q31<TODAY(),"Atrasado",IF(Q31=TODAY(),"Hoje","No prazo")))) -> Atrasado | U31: Na planilha antiga a origem era Instagram, mas a cliente veio pela amiga. | V31: achou caro | W31: =IF(G31="","",IF(OR(G31="Novo contato",G31="Em conversa"),IF(J31="",TODAY(),J31+1),IF(G31="Avaliação marcada",IF(L31="",TODAY(),L31-1),IF(G31="Proposta enviada",IF(J31="",TODAY(),J31+2),IF(G31="Fechou pacote",IF(J31="",TODAY(),J31+7),IF(G31="Em tratamento",IF(M31="",TODAY(),IF(TODAY()<=M31+1,M31+1,EDATE(M31,6)-30)),IF(G31="Pós-venda",IF(J31="",TODAY(),J31+7),IF(G31="Perdido",IF(J31="",TODAY(),J31+60),"")))))))) -> 46269
A32: Cliente 031 | B32: (15) 99999-7217 | C32: Indicação | E32: Microagulhamento | F32: =IF(OR(E32="",E32="A completar",E32="Ainda não sabe"),"",IF(OR(E32="Limpeza de pele",E32="Peeling de diamante",E32="Microagulhamento"),"Rosto","Corpo")) -> Rosto | G32: Em conversa | I32: Nina | J32: 46289 | K32: 0 | P32: =IF(M32="","",EDATE(M32,6)) | Q32: =IF(W32="","",IF(WEEKDAY(W32)=1,W32+1,W32)) -> 46290 | R32: =IF(Q32="","",IF(AND(N(K32)>=3,G32<>"Perdido"),"Mover para Perdido",IF(Q32<TODAY(),"Atrasado",IF(Q32=TODAY(),"Hoje","No prazo")))) -> Atrasado | V32: ligar de novo | W32: =IF(G32="","",IF(OR(G32="Novo contato",G32="Em conversa"),IF(J32="",TODAY(),J32+1),IF(G32="Avaliação marcada",IF(L32="",TODAY(),L32-1),IF(G32="Proposta enviada",IF(J32="",TODAY(),J32+2),IF(G32="Fechou pacote",IF(J32="",TODAY(),J32+7),IF(G32="Em tratamento",IF(M32="",TODAY(),IF(TODAY()<=M32+1,M32+1,EDATE(M32,6)-30)),IF(G32="Pós-venda",IF(J32="",TODAY(),J32+7),IF(G32="Perdido",IF(J32="",TODAY(),J32+60),"")))))))) -> 46290
A33: Cliente 032 | B33: (15) 99999-1890 | C33: Instagram | E33: Peeling de diamante | F33: =IF(OR(E33="",E33="A completar",E33="Ainda não sabe"),"",IF(OR(E33="Limpeza de pele",E33="Peeling de diamante",E33="Microagulhamento"),"Rosto","Corpo")) -> Rosto | G33: Novo contato | I33: Nina | J33: 46293 | K33: 0 | P33: =IF(M33="","",EDATE(M33,6)) | Q33: =IF(W33="","",IF(WEEKDAY(W33)=1,W33+1,W33)) -> 46294 | R33: =IF(Q33="","",IF(AND(N(K33)>=3,G33<>"Perdido"),"Mover para Perdido",IF(Q33<TODAY(),"Atrasado",IF(Q33=TODAY(),"Hoje","No prazo")))) -> Atrasado | S33: Perguntou do resultado: nunca prometer cm ou kg | V33: (em branco) | W33: =IF(G33="","",IF(OR(G33="Novo contato",G33="Em conversa"),IF(J33="",TODAY(),J33+1),IF(G33="Avaliação marcada",IF(L33="",TODAY(),L33-1),IF(G33="Proposta enviada",IF(J33="",TODAY(),J33+2),IF(G33="Fechou pacote",IF(J33="",TODAY(),J33+7),IF(G33="Em tratamento",IF(M33="",TODAY(),IF(TODAY()<=M33+1,M33+1,EDATE(M33,6)-30)),IF(G33="Pós-venda",IF(J33="",TODAY(),J33+7),IF(G33="Perdido",IF(J33="",TODAY(),J33+60),"")))))))) -> 46294
A34: Cliente 033 | B34: (15) 99999-8937 | C34: Indicação | E34: Massagem modeladora | F34: =IF(OR(E34="",E34="A completar",E34="Ainda não sabe"),"",IF(OR(E34="Limpeza de pele",E34="Peeling de diamante",E34="Microagulhamento"),"Rosto","Corpo")) -> Corpo | G34: Proposta enviada | H34: vai pensar | I34: Nina | J34: 46261 | K34: 0 | P34: =IF(M34="","",EDATE(M34,6)) | Q34: =IF(W34="","",IF(WEEKDAY(W34)=1,W34+1,W34)) -> 46263 | R34: =IF(Q34="","",IF(AND(N(K34)>=3,G34<>"Perdido"),"Mover para Perdido",IF(Q34<TODAY(),"Atrasado",IF(Q34=TODAY(),"Hoje","No prazo")))) -> Atrasado | S34: Só pode sábado | V34: vai pensar | W34: =IF(G34="","",IF(OR(G34="Novo contato",G34="Em conversa"),IF(J34="",TODAY(),J34+1),IF(G34="Avaliação marcada",IF(L34="",TODAY(),L34-1),IF(G34="Proposta enviada",IF(J34="",TODAY(),J34+2),IF(G34="Fechou pacote",IF(J34="",TODAY(),J34+7),IF(G34="Em tratamento",IF(M34="",TODAY(),IF(TODAY()<=M34+1,M34+1,EDATE(M34,6)-30)),IF(G34="Pós-venda",IF(J34="",TODAY(),J34+7),IF(G34="Perdido",IF(J34="",TODAY(),J34+60),"")))))))) -> 46263
A35: Cliente 034 | B35: (15) 99999-2736 | C35: Instagram | E35: Limpeza de pele | F35: =IF(OR(E35="",E35="A completar",E35="Ainda não sabe"),"",IF(OR(E35="Limpeza de pele",E35="Peeling de diamante",E35="Microagulhamento"),"Rosto","Corpo")) -> Rosto | G35: Novo contato | I35: Nina | J35: 46229 | K35: 0 | P35: =IF(M35="","",EDATE(M35,6)) | Q35: =IF(W35="","",IF(WEEKDAY(W35)=1,W35+1,W35)) -> 46230 | R35: =IF(Q35="","",IF(AND(N(K35)>=3,G35<>"Perdido"),"Mover para Perdido",IF(Q35<TODAY(),"Atrasado",IF(Q35=TODAY(),"Hoje","No prazo")))) -> Atrasado | S35: Quer parcelar | V35: (em branco) | W35: =IF(G35="","",IF(OR(G35="Novo contato",G35="Em conversa"),IF(J35="",TODAY(),J35+1),IF(G35="Avaliação marcada",IF(L35="",TODAY(),L35-1),IF(G35="Proposta enviada",IF(J35="",TODAY(),J35+2),IF(G35="Fechou pacote",IF(J35="",TODAY(),J35+7),IF(G35="Em tratamento",IF(M35="",TODAY(),IF(TODAY()<=M35+1,M35+1,EDATE(M35,6)-30)),IF(G35="Pós-venda",IF(J35="",TODAY(),J35+7),IF(G35="Perdido",IF(J35="",TODAY(),J35+60),"")))))))) -> 46230
A36: Cliente 035 | B36: (15) 99999-6952 | C36: Instagram | E36: Massagem modeladora | F36: =IF(OR(E36="",E36="A completar",E36="Ainda não sabe"),"",IF(OR(E36="Limpeza de pele",E36="Peeling de diamante",E36="Microagulhamento"),"Rosto","Corpo")) -> Corpo | G36: Em conversa | I36: Nina | J36: 46234 | K36: 0 | P36: =IF(M36="","",EDATE(M36,6)) | Q36: =IF(W36="","",IF(WEEKDAY(W36)=1,W36+1,W36)) -> 46235 | R36: =IF(Q36="","",IF(AND(N(K36)>=3,G36<>"Perdido"),"Mover para Perdido",IF(Q36<TODAY(),"Atrasado",IF(Q36=TODAY(),"Hoje","No prazo")))) -> Atrasado | V36: pediu preço | W36: =IF(G36="","",IF(OR(G36="Novo contato",G36="Em conversa"),IF(J36="",TODAY(),J36+1),IF(G36="Avaliação marcada",IF(L36="",TODAY(),L36-1),IF(G36="Proposta enviada",IF(J36="",TODAY(),J36+2),IF(G36="Fechou pacote",IF(J36="",TODAY(),J36+7),IF(G36="Em tratamento",IF(M36="",TODAY(),IF(TODAY()<=M36+1,M36+1,EDATE(M36,6)-30)),IF(G36="Pós-venda",IF(J36="",TODAY(),J36+7),IF(G36="Perdido",IF(J36="",TODAY(),J36+60),"")))))))) -> 46235
A37: Cliente 036 | B37: (15) 99999-6351 | C37: Instagram (anúncio) | E37: Microagulhamento | F37: =IF(OR(E37="",E37="A completar",E37="Ainda não sabe"),"",IF(OR(E37="Limpeza de pele",E37="Peeling de diamante",E37="Microagulhamento"),"Rosto","Corpo")) -> Rosto | G37: Proposta enviada | I37: Nina | J37: 46235 | K37: 0 | P37: =IF(M37="","",EDATE(M37,6)) | Q37: =IF(W37="","",IF(WEEKDAY(W37)=1,W37+1,W37)) -> 46237 | R37: =IF(Q37="","",IF(AND(N(K37)>=3,G37<>"Perdido"),"Mover para Perdido",IF(Q37<TODAY(),"Atrasado",IF(Q37=TODAY(),"Hoje","No prazo")))) -> Atrasado | V37: fez avaliação | W37: =IF(G37="","",IF(OR(G37="Novo contato",G37="Em conversa"),IF(J37="",TODAY(),J37+1),IF(G37="Avaliação marcada",IF(L37="",TODAY(),L37-1),IF(G37="Proposta enviada",IF(J37="",TODAY(),J37+2),IF(G37="Fechou pacote",IF(J37="",TODAY(),J37+7),IF(G37="Em tratamento",IF(M37="",TODAY(),IF(TODAY()<=M37+1,M37+1,EDATE(M37,6)-30)),IF(G37="Pós-venda",IF(J37="",TODAY(),J37+7),IF(G37="Perdido",IF(J37="",TODAY(),J37+60),"")))))))) -> 46237
A38: Cliente 037 | B38: (15) 99999-0060 | C38: Instagram | E38: Massagem modeladora | F38: =IF(OR(E38="",E38="A completar",E38="Ainda não sabe"),"",IF(OR(E38="Limpeza de pele",E38="Peeling de diamante",E38="Microagulhamento"),"Rosto","Corpo")) -> Corpo | G38: Proposta enviada | I38: Nina | J38: 46242 | K38: 0 | P38: =IF(M38="","",EDATE(M38,6)) | Q38: =IF(W38="","",IF(WEEKDAY(W38)=1,W38+1,W38)) -> 46244 | R38: =IF(Q38="","",IF(AND(N(K38)>=3,G38<>"Perdido"),"Mover para Perdido",IF(Q38<TODAY(),"Atrasado",IF(Q38=TODAY(),"Hoje","No prazo")))) -> Atrasado | S38: Só pode sábado | V38: fez avaliação | W38: =IF(G38="","",IF(OR(G38="Novo contato",G38="Em conversa"),IF(J38="",TODAY(),J38+1),IF(G38="Avaliação marcada",IF(L38="",TODAY(),L38-1),IF(G38="Proposta enviada",IF(J38="",TODAY(),J38+2),IF(G38="Fechou pacote",IF(J38="",TODAY(),J38+7),IF(G38="Em tratamento",IF(M38="",TODAY(),IF(TODAY()<=M38+1,M38+1,EDATE(M38,6)-30)),IF(G38="Pós-venda",IF(J38="",TODAY(),J38+7),IF(G38="Perdido",IF(J38="",TODAY(),J38+60),"")))))))) -> 46244
A39: Cliente 038 | B39: (15) 99999-4051 | C39: Google | E39: Microagulhamento | F39: =IF(OR(E39="",E39="A completar",E39="Ainda não sabe"),"",IF(OR(E39="Limpeza de pele",E39="Peeling de diamante",E39="Microagulhamento"),"Rosto","Corpo")) -> Rosto | G39: Avaliação marcada | I39: Nina | J39: 46251 | K39: 0 | P39: =IF(M39="","",EDATE(M39,6)) | Q39: =IF(W39="","",IF(WEEKDAY(W39)=1,W39+1,W39)) -> 46309 | R39: =IF(Q39="","",IF(AND(N(K39)>=3,G39<>"Perdido"),"Mover para Perdido",IF(Q39<TODAY(),"Atrasado",IF(Q39=TODAY(),"Hoje","No prazo")))) -> Hoje | S39: Já fez em outra clínica | V39: avaliação? | W39: =IF(G39="","",IF(OR(G39="Novo contato",G39="Em conversa"),IF(J39="",TODAY(),J39+1),IF(G39="Avaliação marcada",IF(L39="",TODAY(),L39-1),IF(G39="Proposta enviada",IF(J39="",TODAY(),J39+2),IF(G39="Fechou pacote",IF(J39="",TODAY(),J39+7),IF(G39="Em tratamento",IF(M39="",TODAY(),IF(TODAY()<=M39+1,M39+1,EDATE(M39,6)-30)),IF(G39="Pós-venda",IF(J39="",TODAY(),J39+7),IF(G39="Perdido",IF(J39="",TODAY(),J39+60),"")))))))) -> 46309
A40: Cliente 039 | B40: (15) 99999-7554 | C40: Instagram (anúncio) | E40: Depilação a laser | F40: =IF(OR(E40="",E40="A completar",E40="Ainda não sabe"),"",IF(OR(E40="Limpeza de pele",E40="Peeling de diamante",E40="Microagulhamento"),"Rosto","Corpo")) -> Corpo | G40: Em conversa | I40: Nina | J40: 46275 | K40: 1 | P40: =IF(M40="","",EDATE(M40,6)) | Q40: =IF(W40="","",IF(WEEKDAY(W40)=1,W40+1,W40)) -> 46276 | R40: =IF(Q40="","",IF(AND(N(K40)>=3,G40<>"Perdido"),"Mover para Perdido",IF(Q40<TODAY(),"Atrasado",IF(Q40=TODAY(),"Hoje","No prazo")))) -> Atrasado | S40: Já fez em outra clínica | V40: sumiu | W40: =IF(G40="","",IF(OR(G40="Novo contato",G40="Em conversa"),IF(J40="",TODAY(),J40+1),IF(G40="Avaliação marcada",IF(L40="",TODAY(),L40-1),IF(G40="Proposta enviada",IF(J40="",TODAY(),J40+2),IF(G40="Fechou pacote",IF(J40="",TODAY(),J40+7),IF(G40="Em tratamento",IF(M40="",TODAY(),IF(TODAY()<=M40+1,M40+1,EDATE(M40,6)-30)),IF(G40="Pós-venda",IF(J40="",TODAY(),J40+7),IF(G40="Perdido",IF(J40="",TODAY(),J40+60),"")))))))) -> 46276
A41: Cliente 040 | B41: (15) 99999-0560 | C41: Instagram (anúncio) | E41: Criolipólise | F41: =IF(OR(E41="",E41="A completar",E41="Ainda não sabe"),"",IF(OR(E41="Limpeza de pele",E41="Peeling de diamante",E41="Microagulhamento"),"Rosto","Corpo")) -> Corpo | G41: Avaliação marcada | I41: Nina | K41: 0 | P41: =IF(M41="","",EDATE(M41,6)) | Q41: =IF(W41="","",IF(WEEKDAY(W41)=1,W41+1,W41)) -> 46309 | R41: =IF(Q41="","",IF(AND(N(K41)>=3,G41<>"Perdido"),"Mover para Perdido",IF(Q41<TODAY(),"Atrasado",IF(Q41=TODAY(),"Hoje","No prazo")))) -> Hoje | V41: avaliação? | W41: =IF(G41="","",IF(OR(G41="Novo contato",G41="Em conversa"),IF(J41="",TODAY(),J41+1),IF(G41="Avaliação marcada",IF(L41="",TODAY(),L41-1),IF(G41="Proposta enviada",IF(J41="",TODAY(),J41+2),IF(G41="Fechou pacote",IF(J41="",TODAY(),J41+7),IF(G41="Em tratamento",IF(M41="",TODAY(),IF(TODAY()<=M41+1,M41+1,EDATE(M41,6)-30)),IF(G41="Pós-venda",IF(J41="",TODAY(),J41+7),IF(G41="Perdido",IF(J41="",TODAY(),J41+60),"")))))))) -> 46309
A42: Cliente 041 | B42: (15) 99999-5034 | C42: Instagram | E42: A completar | F42: =IF(OR(E42="",E42="A completar",E42="Ainda não sabe"),"",IF(OR(E42="Limpeza de pele",E42="Peeling de diamante",E42="Microagulhamento"),"Rosto","Corpo")) | G42: Em conversa | I42: Nina | J42: 46223 | K42: 0 | P42: =IF(M42="","",EDATE(M42,6)) | Q42: =IF(W42="","",IF(WEEKDAY(W42)=1,W42+1,W42)) -> 46224 | R42: =IF(Q42="","",IF(AND(N(K42)>=3,G42<>"Perdido"),"Mover para Perdido",IF(Q42<TODAY(),"Atrasado",IF(Q42=TODAY(),"Hoje","No prazo")))) -> Atrasado | S42: Pediu foto de antes e depois: só com autorização escrita | V42: ligar de novo | W42: =IF(G42="","",IF(OR(G42="Novo contato",G42="Em conversa"),IF(J42="",TODAY(),J42+1),IF(G42="Avaliação marcada",IF(L42="",TODAY(),L42-1),IF(G42="Proposta enviada",IF(J42="",TODAY(),J42+2),IF(G42="Fechou pacote",IF(J42="",TODAY(),J42+7),IF(G42="Em tratamento",IF(M42="",TODAY(),IF(TODAY()<=M42+1,M42+1,EDATE(M42,6)-30)),IF(G42="Pós-venda",IF(J42="",TODAY(),J42+7),IF(G42="Perdido",IF(J42="",TODAY(),J42+60),"")))))))) -> 46224
A43: Cliente 042 | B43: (15) 99999-7019 | C43: Instagram | E43: Drenagem linfática | F43: =IF(OR(E43="",E43="A completar",E43="Ainda não sabe"),"",IF(OR(E43="Limpeza de pele",E43="Peeling de diamante",E43="Microagulhamento"),"Rosto","Corpo")) -> Corpo | G43: Proposta enviada | H43: achou caro | I43: Nina | J43: 46230 | K43: 0 | P43: =IF(M43="","",EDATE(M43,6)) | Q43: =IF(W43="","",IF(WEEKDAY(W43)=1,W43+1,W43)) -> 46232 | R43: =IF(Q43="","",IF(AND(N(K43)>=3,G43<>"Perdido"),"Mover para Perdido",IF(Q43<TODAY(),"Atrasado",IF(Q43=TODAY(),"Hoje","No prazo")))) -> Atrasado | V43: achou caro | W43: =IF(G43="","",IF(OR(G43="Novo contato",G43="Em conversa"),IF(J43="",TODAY(),J43+1),IF(G43="Avaliação marcada",IF(L43="",TODAY(),L43-1),IF(G43="Proposta enviada",IF(J43="",TODAY(),J43+2),IF(G43="Fechou pacote",IF(J43="",TODAY(),J43+7),IF(G43="Em tratamento",IF(M43="",TODAY(),IF(TODAY()<=M43+1,M43+1,EDATE(M43,6)-30)),IF(G43="Pós-venda",IF(J43="",TODAY(),J43+7),IF(G43="Perdido",IF(J43="",TODAY(),J43+60),"")))))))) -> 46232
A44: Cliente 043 | B44: (15) 99999-2518 | C44: Indicação | D44: Amiga (confirmar nome) | E44: Microagulhamento | F44: =IF(OR(E44="",E44="A completar",E44="Ainda não sabe"),"",IF(OR(E44="Limpeza de pele",E44="Peeling de diamante",E44="Microagulhamento"),"Rosto","Corpo")) -> Rosto | G44: Proposta enviada | I44: Nina | J44: 46261 | K44: 0 | P44: =IF(M44="","",EDATE(M44,6)) | Q44: =IF(W44="","",IF(WEEKDAY(W44)=1,W44+1,W44)) -> 46263 | R44: =IF(Q44="","",IF(AND(N(K44)>=3,G44<>"Perdido"),"Mover para Perdido",IF(Q44<TODAY(),"Atrasado",IF(Q44=TODAY(),"Hoje","No prazo")))) -> Atrasado | U44: Na planilha antiga a origem era Instagram, mas a cliente veio pela amiga. | V44: fez avaliação | W44: =IF(G44="","",IF(OR(G44="Novo contato",G44="Em conversa"),IF(J44="",TODAY(),J44+1),IF(G44="Avaliação marcada",IF(L44="",TODAY(),L44-1),IF(G44="Proposta enviada",IF(J44="",TODAY(),J44+2),IF(G44="Fechou pacote",IF(J44="",TODAY(),J44+7),IF(G44="Em tratamento",IF(M44="",TODAY(),IF(TODAY()<=M44+1,M44+1,EDATE(M44,6)-30)),IF(G44="Pós-venda",IF(J44="",TODAY(),J44+7),IF(G44="Perdido",IF(J44="",TODAY(),J44+60),"")))))))) -> 46263
A45: Cliente 044 | B45: (15) 99999-1539 | C45: Indicação | E45: Peeling de diamante | F45: =IF(OR(E45="",E45="A completar",E45="Ainda não sabe"),"",IF(OR(E45="Limpeza de pele",E45="Peeling de diamante",E45="Microagulhamento"),"Rosto","Corpo")) -> Rosto | G45: Novo contato | I45: Nina | K45: 0 | P45: =IF(M45="","",EDATE(M45,6)) | Q45: =IF(W45="","",IF(WEEKDAY(W45)=1,W45+1,W45)) -> 46309 | R45: =IF(Q45="","",IF(AND(N(K45)>=3,G45<>"Perdido"),"Mover para Perdido",IF(Q45<TODAY(),"Atrasado",IF(Q45=TODAY(),"Hoje","No prazo")))) -> Hoje | S45: Pediu foto de antes e depois: só com autorização escrita | V45: (em branco) | W45: =IF(G45="","",IF(OR(G45="Novo contato",G45="Em conversa"),IF(J45="",TODAY(),J45+1),IF(G45="Avaliação marcada",IF(L45="",TODAY(),L45-1),IF(G45="Proposta enviada",IF(J45="",TODAY(),J45+2),IF(G45="Fechou pacote",IF(J45="",TODAY(),J45+7),IF(G45="Em tratamento",IF(M45="",TODAY(),IF(TODAY()<=M45+1,M45+1,EDATE(M45,6)-30)),IF(G45="Pós-venda",IF(J45="",TODAY(),J45+7),IF(G45="Perdido",IF(J45="",TODAY(),J45+60),"")))))))) -> 46309
A46: Cliente 045 | B46: (15) 99999-5569 | C46: Indicação | E46: Drenagem linfática | F46: =IF(OR(E46="",E46="A completar",E46="Ainda não sabe"),"",IF(OR(E46="Limpeza de pele",E46="Peeling de diamante",E46="Microagulhamento"),"Rosto","Corpo")) -> Corpo | G46: Novo contato | I46: Nina | J46: 46224 | K46: 0 | P46: =IF(M46="","",EDATE(M46,6)) | Q46: =IF(W46="","",IF(WEEKDAY(W46)=1,W46+1,W46)) -> 46225 | R46: =IF(Q46="","",IF(AND(N(K46)>=3,G46<>"Perdido"),"Mover para Perdido",IF(Q46<TODAY(),"Atrasado",IF(Q46=TODAY(),"Hoje","No prazo")))) -> Atrasado | S46: Perguntou do resultado: nunca prometer cm ou kg | V46: (em branco) | W46: =IF(G46="","",IF(OR(G46="Novo contato",G46="Em conversa"),IF(J46="",TODAY(),J46+1),IF(G46="Avaliação marcada",IF(L46="",TODAY(),L46-1),IF(G46="Proposta enviada",IF(J46="",TODAY(),J46+2),IF(G46="Fechou pacote",IF(J46="",TODAY(),J46+7),IF(G46="Em tratamento",IF(M46="",TODAY(),IF(TODAY()<=M46+1,M46+1,EDATE(M46,6)-30)),IF(G46="Pós-venda",IF(J46="",TODAY(),J46+7),IF(G46="Perdido",IF(J46="",TODAY(),J46+60),"")))))))) -> 46225
A47: Cliente 046 | B47: (15) 99999-0208 | C47: Instagram | E47: Peeling de diamante | F47: =IF(OR(E47="",E47="A completar",E47="Ainda não sabe"),"",IF(OR(E47="Limpeza de pele",E47="Peeling de diamante",E47="Microagulhamento"),"Rosto","Corpo")) -> Rosto | G47: Avaliação marcada | I47: Nina | J47: 46253 | K47: 0 | P47: =IF(M47="","",EDATE(M47,6)) | Q47: =IF(W47="","",IF(WEEKDAY(W47)=1,W47+1,W47)) -> 46309 | R47: =IF(Q47="","",IF(AND(N(K47)>=3,G47<>"Perdido"),"Mover para Perdido",IF(Q47<TODAY(),"Atrasado",IF(Q47=TODAY(),"Hoje","No prazo")))) -> Hoje | S47: Já fez em outra clínica | V47: avaliação? | W47: =IF(G47="","",IF(OR(G47="Novo contato",G47="Em conversa"),IF(J47="",TODAY(),J47+1),IF(G47="Avaliação marcada",IF(L47="",TODAY(),L47-1),IF(G47="Proposta enviada",IF(J47="",TODAY(),J47+2),IF(G47="Fechou pacote",IF(J47="",TODAY(),J47+7),IF(G47="Em tratamento",IF(M47="",TODAY(),IF(TODAY()<=M47+1,M47+1,EDATE(M47,6)-30)),IF(G47="Pós-venda",IF(J47="",TODAY(),J47+7),IF(G47="Perdido",IF(J47="",TODAY(),J47+60),"")))))))) -> 46309
A48: Cliente 047 | B48: (15) 99999-5648 | C48: Indicação | E48: Massagem modeladora | F48: =IF(OR(E48="",E48="A completar",E48="Ainda não sabe"),"",IF(OR(E48="Limpeza de pele",E48="Peeling de diamante",E48="Microagulhamento"),"Rosto","Corpo")) -> Corpo | G48: Em conversa | I48: Nina | J48: 46268 | K48: 0 | P48: =IF(M48="","",EDATE(M48,6)) | Q48: =IF(W48="","",IF(WEEKDAY(W48)=1,W48+1,W48)) -> 46269 | R48: =IF(Q48="","",IF(AND(N(K48)>=3,G48<>"Perdido"),"Mover para Perdido",IF(Q48<TODAY(),"Atrasado",IF(Q48=TODAY(),"Hoje","No prazo")))) -> Atrasado | V48: ligar de novo | W48: =IF(G48="","",IF(OR(G48="Novo contato",G48="Em conversa"),IF(J48="",TODAY(),J48+1),IF(G48="Avaliação marcada",IF(L48="",TODAY(),L48-1),IF(G48="Proposta enviada",IF(J48="",TODAY(),J48+2),IF(G48="Fechou pacote",IF(J48="",TODAY(),J48+7),IF(G48="Em tratamento",IF(M48="",TODAY(),IF(TODAY()<=M48+1,M48+1,EDATE(M48,6)-30)),IF(G48="Pós-venda",IF(J48="",TODAY(),J48+7),IF(G48="Perdido",IF(J48="",TODAY(),J48+60),"")))))))) -> 46269
A49: Cliente 048 | B49: (15) 99999-2053 | C49: Instagram | E49: Limpeza de pele | F49: =IF(OR(E49="",E49="A completar",E49="Ainda não sabe"),"",IF(OR(E49="Limpeza de pele",E49="Peeling de diamante",E49="Microagulhamento"),"Rosto","Corpo")) -> Rosto | G49: Em conversa | I49: Nina | J49: 46255 | K49: 0 | P49: =IF(M49="","",EDATE(M49,6)) | Q49: =IF(W49="","",IF(WEEKDAY(W49)=1,W49+1,W49)) -> 46256 | R49: =IF(Q49="","",IF(AND(N(K49)>=3,G49<>"Perdido"),"Mover para Perdido",IF(Q49<TODAY(),"Atrasado",IF(Q49=TODAY(),"Hoje","No prazo")))) -> Atrasado | S49: Pediu foto de antes e depois: só com autorização escrita | V49: pediu preço | W49: =IF(G49="","",IF(OR(G49="Novo contato",G49="Em conversa"),IF(J49="",TODAY(),J49+1),IF(G49="Avaliação marcada",IF(L49="",TODAY(),L49-1),IF(G49="Proposta enviada",IF(J49="",TODAY(),J49+2),IF(G49="Fechou pacote",IF(J49="",TODAY(),J49+7),IF(G49="Em tratamento",IF(M49="",TODAY(),IF(TODAY()<=M49+1,M49+1,EDATE(M49,6)-30)),IF(G49="Pós-venda",IF(J49="",TODAY(),J49+7),IF(G49="Perdido",IF(J49="",TODAY(),J49+60),"")))))))) -> 46256
A50: Cliente 049 | B50: (15) 99999-8381 | C50: Instagram | E50: A completar | F50: =IF(OR(E50="",E50="A completar",E50="Ainda não sabe"),"",IF(OR(E50="Limpeza de pele",E50="Peeling de diamante",E50="Microagulhamento"),"Rosto","Corpo")) | G50: Fechou pacote | I50: Nina | J50: 46305 | K50: 0 | P50: =IF(M50="","",EDATE(M50,6)) | Q50: =IF(W50="","",IF(WEEKDAY(W50)=1,W50+1,W50)) -> 46312 | R50: =IF(Q50="","",IF(AND(N(K50)>=3,G50<>"Perdido"),"Mover para Perdido",IF(Q50<TODAY(),"Atrasado",IF(Q50=TODAY(),"Hoje","No prazo")))) -> No prazo | S50: Perguntou do resultado: nunca prometer cm ou kg | V50: fechou pacote | W50: =IF(G50="","",IF(OR(G50="Novo contato",G50="Em conversa"),IF(J50="",TODAY(),J50+1),IF(G50="Avaliação marcada",IF(L50="",TODAY(),L50-1),IF(G50="Proposta enviada",IF(J50="",TODAY(),J50+2),IF(G50="Fechou pacote",IF(J50="",TODAY(),J50+7),IF(G50="Em tratamento",IF(M50="",TODAY(),IF(TODAY()<=M50+1,M50+1,EDATE(M50,6)-30)),IF(G50="Pós-venda",IF(J50="",TODAY(),J50+7),IF(G50="Perdido",IF(J50="",TODAY(),J50+60),"")))))))) -> 46312
A51: Cliente 050 | B51: (15) 99999-8179 | C51: A completar | E51: Limpeza de pele | F51: =IF(OR(E51="",E51="A completar",E51="Ainda não sabe"),"",IF(OR(E51="Limpeza de pele",E51="Peeling de diamante",E51="Microagulhamento"),"Rosto","Corpo")) -> Rosto | G51: Em conversa | I51: Nina | J51: 46296 | K51: 1 | P51: =IF(M51="","",EDATE(M51,6)) | Q51: =IF(W51="","",IF(WEEKDAY(W51)=1,W51+1,W51)) -> 46297 | R51: =IF(Q51="","",IF(AND(N(K51)>=3,G51<>"Perdido"),"Mover para Perdido",IF(Q51<TODAY(),"Atrasado",IF(Q51=TODAY(),"Hoje","No prazo")))) -> Atrasado | S51: Pediu foto de antes e depois: só com autorização escrita | V51: não respondeu | W51: =IF(G51="","",IF(OR(G51="Novo contato",G51="Em conversa"),IF(J51="",TODAY(),J51+1),IF(G51="Avaliação marcada",IF(L51="",TODAY(),L51-1),IF(G51="Proposta enviada",IF(J51="",TODAY(),J51+2),IF(G51="Fechou pacote",IF(J51="",TODAY(),J51+7),IF(G51="Em tratamento",IF(M51="",TODAY(),IF(TODAY()<=M51+1,M51+1,EDATE(M51,6)-30)),IF(G51="Pós-venda",IF(J51="",TODAY(),J51+7),IF(G51="Perdido",IF(J51="",TODAY(),J51+60),"")))))))) -> 46297
A52: Cliente 051 | B52: (15) 99999-2041 | C52: Indicação | E52: Peeling de diamante | F52: =IF(OR(E52="",E52="A completar",E52="Ainda não sabe"),"",IF(OR(E52="Limpeza de pele",E52="Peeling de diamante",E52="Microagulhamento"),"Rosto","Corpo")) -> Rosto | G52: Em conversa | I52: Nina | J52: 46258 | K52: 1 | P52: =IF(M52="","",EDATE(M52,6)) | Q52: =IF(W52="","",IF(WEEKDAY(W52)=1,W52+1,W52)) -> 46259 | R52: =IF(Q52="","",IF(AND(N(K52)>=3,G52<>"Perdido"),"Mover para Perdido",IF(Q52<TODAY(),"Atrasado",IF(Q52=TODAY(),"Hoje","No prazo")))) -> Atrasado | S52: Prefere áudio | V52: sumiu | W52: =IF(G52="","",IF(OR(G52="Novo contato",G52="Em conversa"),IF(J52="",TODAY(),J52+1),IF(G52="Avaliação marcada",IF(L52="",TODAY(),L52-1),IF(G52="Proposta enviada",IF(J52="",TODAY(),J52+2),IF(G52="Fechou pacote",IF(J52="",TODAY(),J52+7),IF(G52="Em tratamento",IF(M52="",TODAY(),IF(TODAY()<=M52+1,M52+1,EDATE(M52,6)-30)),IF(G52="Pós-venda",IF(J52="",TODAY(),J52+7),IF(G52="Perdido",IF(J52="",TODAY(),J52+60),"")))))))) -> 46259
A53: Cliente 052 | B53: (15) 99999-6787 | C53: Indicação | E53: Drenagem linfática | F53: =IF(OR(E53="",E53="A completar",E53="Ainda não sabe"),"",IF(OR(E53="Limpeza de pele",E53="Peeling de diamante",E53="Microagulhamento"),"Rosto","Corpo")) -> Corpo | G53: Avaliação marcada | I53: Nina | J53: 46232 | K53: 0 | P53: =IF(M53="","",EDATE(M53,6)) | Q53: =IF(W53="","",IF(WEEKDAY(W53)=1,W53+1,W53)) -> 46309 | R53: =IF(Q53="","",IF(AND(N(K53)>=3,G53<>"Perdido"),"Mover para Perdido",IF(Q53<TODAY(),"Atrasado",IF(Q53=TODAY(),"Hoje","No prazo")))) -> Hoje | S53: Já fez em outra clínica | V53: remarcar | W53: =IF(G53="","",IF(OR(G53="Novo contato",G53="Em conversa"),IF(J53="",TODAY(),J53+1),IF(G53="Avaliação marcada",IF(L53="",TODAY(),L53-1),IF(G53="Proposta enviada",IF(J53="",TODAY(),J53+2),IF(G53="Fechou pacote",IF(J53="",TODAY(),J53+7),IF(G53="Em tratamento",IF(M53="",TODAY(),IF(TODAY()<=M53+1,M53+1,EDATE(M53,6)-30)),IF(G53="Pós-venda",IF(J53="",TODAY(),J53+7),IF(G53="Perdido",IF(J53="",TODAY(),J53+60),"")))))))) -> 46309
A54: Cliente 053 | B54: (15) 99999-9243 | C54: Indicação | D54: Amiga (confirmar nome) | E54: Limpeza de pele | F54: =IF(OR(E54="",E54="A completar",E54="Ainda não sabe"),"",IF(OR(E54="Limpeza de pele",E54="Peeling de diamante",E54="Microagulhamento"),"Rosto","Corpo")) -> Rosto | G54: Proposta enviada | I54: Nina | J54: 46272 | K54: 0 | P54: =IF(M54="","",EDATE(M54,6)) | Q54: =IF(W54="","",IF(WEEKDAY(W54)=1,W54+1,W54)) -> 46274 | R54: =IF(Q54="","",IF(AND(N(K54)>=3,G54<>"Perdido"),"Mover para Perdido",IF(Q54<TODAY(),"Atrasado",IF(Q54=TODAY(),"Hoje","No prazo")))) -> Atrasado | U54: Na planilha antiga a origem era Instagram, mas a cliente veio pela amiga. | V54: fez avaliação | W54: =IF(G54="","",IF(OR(G54="Novo contato",G54="Em conversa"),IF(J54="",TODAY(),J54+1),IF(G54="Avaliação marcada",IF(L54="",TODAY(),L54-1),IF(G54="Proposta enviada",IF(J54="",TODAY(),J54+2),IF(G54="Fechou pacote",IF(J54="",TODAY(),J54+7),IF(G54="Em tratamento",IF(M54="",TODAY(),IF(TODAY()<=M54+1,M54+1,EDATE(M54,6)-30)),IF(G54="Pós-venda",IF(J54="",TODAY(),J54+7),IF(G54="Perdido",IF(J54="",TODAY(),J54+60),"")))))))) -> 46274
A55: Cliente 054 | B55: (15) 99999-5318 | C55: Indicação | E55: Depilação a laser | F55: =IF(OR(E55="",E55="A completar",E55="Ainda não sabe"),"",IF(OR(E55="Limpeza de pele",E55="Peeling de diamante",E55="Microagulhamento"),"Rosto","Corpo")) -> Corpo | G55: Em conversa | I55: Nina | J55: 46223 | K55: 1 | P55: =IF(M55="","",EDATE(M55,6)) | Q55: =IF(W55="","",IF(WEEKDAY(W55)=1,W55+1,W55)) -> 46224 | R55: =IF(Q55="","",IF(AND(N(K55)>=3,G55<>"Perdido"),"Mover para Perdido",IF(Q55<TODAY(),"Atrasado",IF(Q55=TODAY(),"Hoje","No prazo")))) -> Atrasado | S55: Pediu foto de antes e depois: só com autorização escrita | V55: sumiu | W55: =IF(G55="","",IF(OR(G55="Novo contato",G55="Em conversa"),IF(J55="",TODAY(),J55+1),IF(G55="Avaliação marcada",IF(L55="",TODAY(),L55-1),IF(G55="Proposta enviada",IF(J55="",TODAY(),J55+2),IF(G55="Fechou pacote",IF(J55="",TODAY(),J55+7),IF(G55="Em tratamento",IF(M55="",TODAY(),IF(TODAY()<=M55+1,M55+1,EDATE(M55,6)-30)),IF(G55="Pós-venda",IF(J55="",TODAY(),J55+7),IF(G55="Perdido",IF(J55="",TODAY(),J55+60),"")))))))) -> 46224
A56: Cliente 055 | B56: (15) 99999-1459 | C56: Instagram | E56: Criolipólise | F56: =IF(OR(E56="",E56="A completar",E56="Ainda não sabe"),"",IF(OR(E56="Limpeza de pele",E56="Peeling de diamante",E56="Microagulhamento"),"Rosto","Corpo")) -> Corpo | G56: Proposta enviada | H56: vai pensar | I56: Nina | K56: 0 | P56: =IF(M56="","",EDATE(M56,6)) | Q56: =IF(W56="","",IF(WEEKDAY(W56)=1,W56+1,W56)) -> 46309 | R56: =IF(Q56="","",IF(AND(N(K56)>=3,G56<>"Perdido"),"Mover para Perdido",IF(Q56<TODAY(),"Atrasado",IF(Q56=TODAY(),"Hoje","No prazo")))) -> Hoje | S56: Pediu foto de antes e depois: só com autorização escrita | V56: vai pensar | W56: =IF(G56="","",IF(OR(G56="Novo contato",G56="Em conversa"),IF(J56="",TODAY(),J56+1),IF(G56="Avaliação marcada",IF(L56="",TODAY(),L56-1),IF(G56="Proposta enviada",IF(J56="",TODAY(),J56+2),IF(G56="Fechou pacote",IF(J56="",TODAY(),J56+7),IF(G56="Em tratamento",IF(M56="",TODAY(),IF(TODAY()<=M56+1,M56+1,EDATE(M56,6)-30)),IF(G56="Pós-venda",IF(J56="",TODAY(),J56+7),IF(G56="Perdido",IF(J56="",TODAY(),J56+60),"")))))))) -> 46309
A57: Cliente 056 | B57: (15) 99999-5134 | C57: Instagram | E57: Drenagem linfática | F57: =IF(OR(E57="",E57="A completar",E57="Ainda não sabe"),"",IF(OR(E57="Limpeza de pele",E57="Peeling de diamante",E57="Microagulhamento"),"Rosto","Corpo")) -> Corpo | G57: Avaliação marcada | I57: Nina | J57: 46272 | K57: 0 | P57: =IF(M57="","",EDATE(M57,6)) | Q57: =IF(W57="","",IF(WEEKDAY(W57)=1,W57+1,W57)) -> 46309 | R57: =IF(Q57="","",IF(AND(N(K57)>=3,G57<>"Perdido"),"Mover para Perdido",IF(Q57<TODAY(),"Atrasado",IF(Q57=TODAY(),"Hoje","No prazo")))) -> Hoje | V57: avaliação? | W57: =IF(G57="","",IF(OR(G57="Novo contato",G57="Em conversa"),IF(J57="",TODAY(),J57+1),IF(G57="Avaliação marcada",IF(L57="",TODAY(),L57-1),IF(G57="Proposta enviada",IF(J57="",TODAY(),J57+2),IF(G57="Fechou pacote",IF(J57="",TODAY(),J57+7),IF(G57="Em tratamento",IF(M57="",TODAY(),IF(TODAY()<=M57+1,M57+1,EDATE(M57,6)-30)),IF(G57="Pós-venda",IF(J57="",TODAY(),J57+7),IF(G57="Perdido",IF(J57="",TODAY(),J57+60),"")))))))) -> 46309
A58: Cliente 057 | B58: (15) 99999-7167 | C58: Instagram | E58: Microagulhamento | F58: =IF(OR(E58="",E58="A completar",E58="Ainda não sabe"),"",IF(OR(E58="Limpeza de pele",E58="Peeling de diamante",E58="Microagulhamento"),"Rosto","Corpo")) -> Rosto | G58: Avaliação marcada | I58: Nina | K58: 0 | P58: =IF(M58="","",EDATE(M58,6)) | Q58: =IF(W58="","",IF(WEEKDAY(W58)=1,W58+1,W58)) -> 46309 | R58: =IF(Q58="","",IF(AND(N(K58)>=3,G58<>"Perdido"),"Mover para Perdido",IF(Q58<TODAY(),"Atrasado",IF(Q58=TODAY(),"Hoje","No prazo")))) -> Hoje | V58: remarcar | W58: =IF(G58="","",IF(OR(G58="Novo contato",G58="Em conversa"),IF(J58="",TODAY(),J58+1),IF(G58="Avaliação marcada",IF(L58="",TODAY(),L58-1),IF(G58="Proposta enviada",IF(J58="",TODAY(),J58+2),IF(G58="Fechou pacote",IF(J58="",TODAY(),J58+7),IF(G58="Em tratamento",IF(M58="",TODAY(),IF(TODAY()<=M58+1,M58+1,EDATE(M58,6)-30)),IF(G58="Pós-venda",IF(J58="",TODAY(),J58+7),IF(G58="Perdido",IF(J58="",TODAY(),J58+60),"")))))))) -> 46309
A59: Cliente 058 | B59: (15) 99999-2540 | C59: Instagram | E59: Drenagem linfática | F59: =IF(OR(E59="",E59="A completar",E59="Ainda não sabe"),"",IF(OR(E59="Limpeza de pele",E59="Peeling de diamante",E59="Microagulhamento"),"Rosto","Corpo")) -> Corpo | G59: Fechou pacote | I59: Nina | J59: 46285 | K59: 0 | P59: =IF(M59="","",EDATE(M59,6)) | Q59: =IF(W59="","",IF(WEEKDAY(W59)=1,W59+1,W59)) -> 46293 | R59: =IF(Q59="","",IF(AND(N(K59)>=3,G59<>"Perdido"),"Mover para Perdido",IF(Q59<TODAY(),"Atrasado",IF(Q59=TODAY(),"Hoje","No prazo")))) -> Atrasado | S59: Prefere áudio | V59: fechou pacote | W59: =IF(G59="","",IF(OR(G59="Novo contato",G59="Em conversa"),IF(J59="",TODAY(),J59+1),IF(G59="Avaliação marcada",IF(L59="",TODAY(),L59-1),IF(G59="Proposta enviada",IF(J59="",TODAY(),J59+2),IF(G59="Fechou pacote",IF(J59="",TODAY(),J59+7),IF(G59="Em tratamento",IF(M59="",TODAY(),IF(TODAY()<=M59+1,M59+1,EDATE(M59,6)-30)),IF(G59="Pós-venda",IF(J59="",TODAY(),J59+7),IF(G59="Perdido",IF(J59="",TODAY(),J59+60),"")))))))) -> 46292
A60: Cliente 059 | B60: (15) 99999-8535 | C60: Instagram | E60: Limpeza de pele | F60: =IF(OR(E60="",E60="A completar",E60="Ainda não sabe"),"",IF(OR(E60="Limpeza de pele",E60="Peeling de diamante",E60="Microagulhamento"),"Rosto","Corpo")) -> Rosto | G60: Avaliação marcada | I60: Nina | J60: 46229 | K60: 0 | P60: =IF(M60="","",EDATE(M60,6)) | Q60: =IF(W60="","",IF(WEEKDAY(W60)=1,W60+1,W60)) -> 46309 | R60: =IF(Q60="","",IF(AND(N(K60)>=3,G60<>"Perdido"),"Mover para Perdido",IF(Q60<TODAY(),"Atrasado",IF(Q60=TODAY(),"Hoje","No prazo")))) -> Hoje | S60: Perguntou do resultado: nunca prometer cm ou kg | V60: remarcar | W60: =IF(G60="","",IF(OR(G60="Novo contato",G60="Em conversa"),IF(J60="",TODAY(),J60+1),IF(G60="Avaliação marcada",IF(L60="",TODAY(),L60-1),IF(G60="Proposta enviada",IF(J60="",TODAY(),J60+2),IF(G60="Fechou pacote",IF(J60="",TODAY(),J60+7),IF(G60="Em tratamento",IF(M60="",TODAY(),IF(TODAY()<=M60+1,M60+1,EDATE(M60,6)-30)),IF(G60="Pós-venda",IF(J60="",TODAY(),J60+7),IF(G60="Perdido",IF(J60="",TODAY(),J60+60),"")))))))) -> 46309
A61: Cliente 060 | B61: (15) 99999-4009 | C61: Indicação | E61: Massagem modeladora | F61: =IF(OR(E61="",E61="A completar",E61="Ainda não sabe"),"",IF(OR(E61="Limpeza de pele",E61="Peeling de diamante",E61="Microagulhamento"),"Rosto","Corpo")) -> Corpo | G61: Em conversa | I61: Nina | J61: 46262 | K61: 0 | P61: =IF(M61="","",EDATE(M61,6)) | Q61: =IF(W61="","",IF(WEEKDAY(W61)=1,W61+1,W61)) -> 46263 | R61: =IF(Q61="","",IF(AND(N(K61)>=3,G61<>"Perdido"),"Mover para Perdido",IF(Q61<TODAY(),"Atrasado",IF(Q61=TODAY(),"Hoje","No prazo")))) -> Atrasado | S61: Pediu foto de antes e depois: só com autorização escrita | V61: ligar de novo | W61: =IF(G61="","",IF(OR(G61="Novo contato",G61="Em conversa"),IF(J61="",TODAY(),J61+1),IF(G61="Avaliação marcada",IF(L61="",TODAY(),L61-1),IF(G61="Proposta enviada",IF(J61="",TODAY(),J61+2),IF(G61="Fechou pacote",IF(J61="",TODAY(),J61+7),IF(G61="Em tratamento",IF(M61="",TODAY(),IF(TODAY()<=M61+1,M61+1,EDATE(M61,6)-30)),IF(G61="Pós-venda",IF(J61="",TODAY(),J61+7),IF(G61="Perdido",IF(J61="",TODAY(),J61+60),"")))))))) -> 46263
A62: Cliente 061 | B62: (15) 99999-4590 | C62: Indicação | E62: Limpeza de pele | F62: =IF(OR(E62="",E62="A completar",E62="Ainda não sabe"),"",IF(OR(E62="Limpeza de pele",E62="Peeling de diamante",E62="Microagulhamento"),"Rosto","Corpo")) -> Rosto | G62: Proposta enviada | H62: achou caro | I62: Nina | J62: 46276 | K62: 0 | P62: =IF(M62="","",EDATE(M62,6)) | Q62: =IF(W62="","",IF(WEEKDAY(W62)=1,W62+1,W62)) -> 46279 | R62: =IF(Q62="","",IF(AND(N(K62)>=3,G62<>"Perdido"),"Mover para Perdido",IF(Q62<TODAY(),"Atrasado",IF(Q62=TODAY(),"Hoje","No prazo")))) -> Atrasado | V62: achou caro | W62: =IF(G62="","",IF(OR(G62="Novo contato",G62="Em conversa"),IF(J62="",TODAY(),J62+1),IF(G62="Avaliação marcada",IF(L62="",TODAY(),L62-1),IF(G62="Proposta enviada",IF(J62="",TODAY(),J62+2),IF(G62="Fechou pacote",IF(J62="",TODAY(),J62+7),IF(G62="Em tratamento",IF(M62="",TODAY(),IF(TODAY()<=M62+1,M62+1,EDATE(M62,6)-30)),IF(G62="Pós-venda",IF(J62="",TODAY(),J62+7),IF(G62="Perdido",IF(J62="",TODAY(),J62+60),"")))))))) -> 46278
A63: Cliente 062 | B63: (15) 99999-1956 | C63: Indicação | E63: Criolipólise | F63: =IF(OR(E63="",E63="A completar",E63="Ainda não sabe"),"",IF(OR(E63="Limpeza de pele",E63="Peeling de diamante",E63="Microagulhamento"),"Rosto","Corpo")) -> Corpo | G63: Avaliação marcada | I63: Nina | K63: 0 | P63: =IF(M63="","",EDATE(M63,6)) | Q63: =IF(W63="","",IF(WEEKDAY(W63)=1,W63+1,W63)) -> 46309 | R63: =IF(Q63="","",IF(AND(N(K63)>=3,G63<>"Perdido"),"Mover para Perdido",IF(Q63<TODAY(),"Atrasado",IF(Q63=TODAY(),"Hoje","No prazo")))) -> Hoje | S63: Prefere áudio | V63: marcou avaliação | W63: =IF(G63="","",IF(OR(G63="Novo contato",G63="Em conversa"),IF(J63="",TODAY(),J63+1),IF(G63="Avaliação marcada",IF(L63="",TODAY(),L63-1),IF(G63="Proposta enviada",IF(J63="",TODAY(),J63+2),IF(G63="Fechou pacote",IF(J63="",TODAY(),J63+7),IF(G63="Em tratamento",IF(M63="",TODAY(),IF(TODAY()<=M63+1,M63+1,EDATE(M63,6)-30)),IF(G63="Pós-venda",IF(J63="",TODAY(),J63+7),IF(G63="Perdido",IF(J63="",TODAY(),J63+60),"")))))))) -> 46309
A64: Cliente 063 | B64: (15) 99999-8077 | C64: Instagram (anúncio) | E64: Limpeza de pele | F64: =IF(OR(E64="",E64="A completar",E64="Ainda não sabe"),"",IF(OR(E64="Limpeza de pele",E64="Peeling de diamante",E64="Microagulhamento"),"Rosto","Corpo")) -> Rosto | G64: Em conversa | I64: Nina | K64: 0 | P64: =IF(M64="","",EDATE(M64,6)) | Q64: =IF(W64="","",IF(WEEKDAY(W64)=1,W64+1,W64)) -> 46309 | R64: =IF(Q64="","",IF(AND(N(K64)>=3,G64<>"Perdido"),"Mover para Perdido",IF(Q64<TODAY(),"Atrasado",IF(Q64=TODAY(),"Hoje","No prazo")))) -> Hoje | S64: Prefere áudio | V64: pediu preço | W64: =IF(G64="","",IF(OR(G64="Novo contato",G64="Em conversa"),IF(J64="",TODAY(),J64+1),IF(G64="Avaliação marcada",IF(L64="",TODAY(),L64-1),IF(G64="Proposta enviada",IF(J64="",TODAY(),J64+2),IF(G64="Fechou pacote",IF(J64="",TODAY(),J64+7),IF(G64="Em tratamento",IF(M64="",TODAY(),IF(TODAY()<=M64+1,M64+1,EDATE(M64,6)-30)),IF(G64="Pós-venda",IF(J64="",TODAY(),J64+7),IF(G64="Perdido",IF(J64="",TODAY(),J64+60),"")))))))) -> 46309
A65: Cliente 064 | B65: (15) 99999-7825 | C65: Indicação | E65: A completar | F65: =IF(OR(E65="",E65="A completar",E65="Ainda não sabe"),"",IF(OR(E65="Limpeza de pele",E65="Peeling de diamante",E65="Microagulhamento"),"Rosto","Corpo")) | G65: Fechou pacote | I65: Nina | J65: 46292 | K65: 0 | P65: =IF(M65="","",EDATE(M65,6)) | Q65: =IF(W65="","",IF(WEEKDAY(W65)=1,W65+1,W65)) -> 46300 | R65: =IF(Q65="","",IF(AND(N(K65)>=3,G65<>"Perdido"),"Mover para Perdido",IF(Q65<TODAY(),"Atrasado",IF(Q65=TODAY(),"Hoje","No prazo")))) -> Atrasado | S65: Só pode sábado | V65: fechou pacote | W65: =IF(G65="","",IF(OR(G65="Novo contato",G65="Em conversa"),IF(J65="",TODAY(),J65+1),IF(G65="Avaliação marcada",IF(L65="",TODAY(),L65-1),IF(G65="Proposta enviada",IF(J65="",TODAY(),J65+2),IF(G65="Fechou pacote",IF(J65="",TODAY(),J65+7),IF(G65="Em tratamento",IF(M65="",TODAY(),IF(TODAY()<=M65+1,M65+1,EDATE(M65,6)-30)),IF(G65="Pós-venda",IF(J65="",TODAY(),J65+7),IF(G65="Perdido",IF(J65="",TODAY(),J65+60),"")))))))) -> 46299
A66: Cliente 065 | B66: (15) 99999-8027 | C66: Instagram | E66: Limpeza de pele | F66: =IF(OR(E66="",E66="A completar",E66="Ainda não sabe"),"",IF(OR(E66="Limpeza de pele",E66="Peeling de diamante",E66="Microagulhamento"),"Rosto","Corpo")) -> Rosto | G66: Proposta enviada | I66: Nina | K66: 0 | P66: =IF(M66="","",EDATE(M66,6)) | Q66: =IF(W66="","",IF(WEEKDAY(W66)=1,W66+1,W66)) -> 46309 | R66: =IF(Q66="","",IF(AND(N(K66)>=3,G66<>"Perdido"),"Mover para Perdido",IF(Q66<TODAY(),"Atrasado",IF(Q66=TODAY(),"Hoje","No prazo")))) -> Hoje | S66: Já fez em outra clínica | V66: fez avaliação | W66: =IF(G66="","",IF(OR(G66="Novo contato",G66="Em conversa"),IF(J66="",TODAY(),J66+1),IF(G66="Avaliação marcada",IF(L66="",TODAY(),L66-1),IF(G66="Proposta enviada",IF(J66="",TODAY(),J66+2),IF(G66="Fechou pacote",IF(J66="",TODAY(),J66+7),IF(G66="Em tratamento",IF(M66="",TODAY(),IF(TODAY()<=M66+1,M66+1,EDATE(M66,6)-30)),IF(G66="Pós-venda",IF(J66="",TODAY(),J66+7),IF(G66="Perdido",IF(J66="",TODAY(),J66+60),"")))))))) -> 46309
A67: Cliente 066 | B67: (15) 99999-2280 | C67: Instagram | E67: Criolipólise | F67: =IF(OR(E67="",E67="A completar",E67="Ainda não sabe"),"",IF(OR(E67="Limpeza de pele",E67="Peeling de diamante",E67="Microagulhamento"),"Rosto","Corpo")) -> Corpo | G67: Avaliação marcada | I67: Nina | J67: 46224 | K67: 0 | P67: =IF(M67="","",EDATE(M67,6)) | Q67: =IF(W67="","",IF(WEEKDAY(W67)=1,W67+1,W67)) -> 46309 | R67: =IF(Q67="","",IF(AND(N(K67)>=3,G67<>"Perdido"),"Mover para Perdido",IF(Q67<TODAY(),"Atrasado",IF(Q67=TODAY(),"Hoje","No prazo")))) -> Hoje | S67: Só pode sábado | V67: marcou avaliação | W67: =IF(G67="","",IF(OR(G67="Novo contato",G67="Em conversa"),IF(J67="",TODAY(),J67+1),IF(G67="Avaliação marcada",IF(L67="",TODAY(),L67-1),IF(G67="Proposta enviada",IF(J67="",TODAY(),J67+2),IF(G67="Fechou pacote",IF(J67="",TODAY(),J67+7),IF(G67="Em tratamento",IF(M67="",TODAY(),IF(TODAY()<=M67+1,M67+1,EDATE(M67,6)-30)),IF(G67="Pós-venda",IF(J67="",TODAY(),J67+7),IF(G67="Perdido",IF(J67="",TODAY(),J67+60),"")))))))) -> 46309
A68: Cliente 067 | B68: (15) 99999-7148 | C68: Instagram | E68: Peeling de diamante | F68: =IF(OR(E68="",E68="A completar",E68="Ainda não sabe"),"",IF(OR(E68="Limpeza de pele",E68="Peeling de diamante",E68="Microagulhamento"),"Rosto","Corpo")) -> Rosto | G68: Fechou pacote | I68: Nina | J68: 46242 | K68: 0 | P68: =IF(M68="","",EDATE(M68,6)) | Q68: =IF(W68="","",IF(WEEKDAY(W68)=1,W68+1,W68)) -> 46249 | R68: =IF(Q68="","",IF(AND(N(K68)>=3,G68<>"Perdido"),"Mover para Perdido",IF(Q68<TODAY(),"Atrasado",IF(Q68=TODAY(),"Hoje","No prazo")))) -> Atrasado | S68: Só pode sábado | V68: fechou pacote | W68: =IF(G68="","",IF(OR(G68="Novo contato",G68="Em conversa"),IF(J68="",TODAY(),J68+1),IF(G68="Avaliação marcada",IF(L68="",TODAY(),L68-1),IF(G68="Proposta enviada",IF(J68="",TODAY(),J68+2),IF(G68="Fechou pacote",IF(J68="",TODAY(),J68+7),IF(G68="Em tratamento",IF(M68="",TODAY(),IF(TODAY()<=M68+1,M68+1,EDATE(M68,6)-30)),IF(G68="Pós-venda",IF(J68="",TODAY(),J68+7),IF(G68="Perdido",IF(J68="",TODAY(),J68+60),"")))))))) -> 46249
A69: Cliente 068 | B69: (15) 99999-1752 | C69: Instagram | E69: Criolipólise | F69: =IF(OR(E69="",E69="A completar",E69="Ainda não sabe"),"",IF(OR(E69="Limpeza de pele",E69="Peeling de diamante",E69="Microagulhamento"),"Rosto","Corpo")) -> Corpo | G69: Em conversa | I69: Nina | J69: 46267 | K69: 0 | P69: =IF(M69="","",EDATE(M69,6)) | Q69: =IF(W69="","",IF(WEEKDAY(W69)=1,W69+1,W69)) -> 46268 | R69: =IF(Q69="","",IF(AND(N(K69)>=3,G69<>"Perdido"),"Mover para Perdido",IF(Q69<TODAY(),"Atrasado",IF(Q69=TODAY(),"Hoje","No prazo")))) -> Atrasado | V69: ligar de novo | W69: =IF(G69="","",IF(OR(G69="Novo contato",G69="Em conversa"),IF(J69="",TODAY(),J69+1),IF(G69="Avaliação marcada",IF(L69="",TODAY(),L69-1),IF(G69="Proposta enviada",IF(J69="",TODAY(),J69+2),IF(G69="Fechou pacote",IF(J69="",TODAY(),J69+7),IF(G69="Em tratamento",IF(M69="",TODAY(),IF(TODAY()<=M69+1,M69+1,EDATE(M69,6)-30)),IF(G69="Pós-venda",IF(J69="",TODAY(),J69+7),IF(G69="Perdido",IF(J69="",TODAY(),J69+60),"")))))))) -> 46268
A70: Cliente 069 | B70: (15) 99999-0928 | C70: A completar | E70: Limpeza de pele | F70: =IF(OR(E70="",E70="A completar",E70="Ainda não sabe"),"",IF(OR(E70="Limpeza de pele",E70="Peeling de diamante",E70="Microagulhamento"),"Rosto","Corpo")) -> Rosto | G70: Em conversa | I70: Nina | J70: 46303 | K70: 1 | P70: =IF(M70="","",EDATE(M70,6)) | Q70: =IF(W70="","",IF(WEEKDAY(W70)=1,W70+1,W70)) -> 46304 | R70: =IF(Q70="","",IF(AND(N(K70)>=3,G70<>"Perdido"),"Mover para Perdido",IF(Q70<TODAY(),"Atrasado",IF(Q70=TODAY(),"Hoje","No prazo")))) -> Atrasado | S70: Perguntou do resultado: nunca prometer cm ou kg | V70: não respondeu | W70: =IF(G70="","",IF(OR(G70="Novo contato",G70="Em conversa"),IF(J70="",TODAY(),J70+1),IF(G70="Avaliação marcada",IF(L70="",TODAY(),L70-1),IF(G70="Proposta enviada",IF(J70="",TODAY(),J70+2),IF(G70="Fechou pacote",IF(J70="",TODAY(),J70+7),IF(G70="Em tratamento",IF(M70="",TODAY(),IF(TODAY()<=M70+1,M70+1,EDATE(M70,6)-30)),IF(G70="Pós-venda",IF(J70="",TODAY(),J70+7),IF(G70="Perdido",IF(J70="",TODAY(),J70+60),"")))))))) -> 46304
A71: Cliente 070 | B71: (15) 99999-2526 | C71: A completar | E71: Drenagem linfática | F71: =IF(OR(E71="",E71="A completar",E71="Ainda não sabe"),"",IF(OR(E71="Limpeza de pele",E71="Peeling de diamante",E71="Microagulhamento"),"Rosto","Corpo")) -> Corpo | G71: Em conversa | I71: Nina | J71: 46293 | K71: 1 | P71: =IF(M71="","",EDATE(M71,6)) | Q71: =IF(W71="","",IF(WEEKDAY(W71)=1,W71+1,W71)) -> 46294 | R71: =IF(Q71="","",IF(AND(N(K71)>=3,G71<>"Perdido"),"Mover para Perdido",IF(Q71<TODAY(),"Atrasado",IF(Q71=TODAY(),"Hoje","No prazo")))) -> Atrasado | S71: Perguntou do resultado: nunca prometer cm ou kg | V71: sumiu | W71: =IF(G71="","",IF(OR(G71="Novo contato",G71="Em conversa"),IF(J71="",TODAY(),J71+1),IF(G71="Avaliação marcada",IF(L71="",TODAY(),L71-1),IF(G71="Proposta enviada",IF(J71="",TODAY(),J71+2),IF(G71="Fechou pacote",IF(J71="",TODAY(),J71+7),IF(G71="Em tratamento",IF(M71="",TODAY(),IF(TODAY()<=M71+1,M71+1,EDATE(M71,6)-30)),IF(G71="Pós-venda",IF(J71="",TODAY(),J71+7),IF(G71="Perdido",IF(J71="",TODAY(),J71+60),"")))))))) -> 46294
A72: Cliente 071 | B72: (15) 99999-6556 | C72: Indicação | D72: Amiga (confirmar nome) | E72: Limpeza de pele | F72: =IF(OR(E72="",E72="A completar",E72="Ainda não sabe"),"",IF(OR(E72="Limpeza de pele",E72="Peeling de diamante",E72="Microagulhamento"),"Rosto","Corpo")) -> Rosto | G72: Novo contato | I72: Nina | J72: 46266 | K72: 0 | P72: =IF(M72="","",EDATE(M72,6)) | Q72: =IF(W72="","",IF(WEEKDAY(W72)=1,W72+1,W72)) -> 46267 | R72: =IF(Q72="","",IF(AND(N(K72)>=3,G72<>"Perdido"),"Mover para Perdido",IF(Q72<TODAY(),"Atrasado",IF(Q72=TODAY(),"Hoje","No prazo")))) -> Atrasado | V72: (em branco) | W72: =IF(G72="","",IF(OR(G72="Novo contato",G72="Em conversa"),IF(J72="",TODAY(),J72+1),IF(G72="Avaliação marcada",IF(L72="",TODAY(),L72-1),IF(G72="Proposta enviada",IF(J72="",TODAY(),J72+2),IF(G72="Fechou pacote",IF(J72="",TODAY(),J72+7),IF(G72="Em tratamento",IF(M72="",TODAY(),IF(TODAY()<=M72+1,M72+1,EDATE(M72,6)-30)),IF(G72="Pós-venda",IF(J72="",TODAY(),J72+7),IF(G72="Perdido",IF(J72="",TODAY(),J72+60),"")))))))) -> 46267
A73: Cliente 072 | B73: (15) 99999-9733 | C73: Instagram | E73: A completar | F73: =IF(OR(E73="",E73="A completar",E73="Ainda não sabe"),"",IF(OR(E73="Limpeza de pele",E73="Peeling de diamante",E73="Microagulhamento"),"Rosto","Corpo")) | G73: Em conversa | I73: Nina | J73: 46274 | K73: 1 | P73: =IF(M73="","",EDATE(M73,6)) | Q73: =IF(W73="","",IF(WEEKDAY(W73)=1,W73+1,W73)) -> 46275 | R73: =IF(Q73="","",IF(AND(N(K73)>=3,G73<>"Perdido"),"Mover para Perdido",IF(Q73<TODAY(),"Atrasado",IF(Q73=TODAY(),"Hoje","No prazo")))) -> Atrasado | V73: não respondeu | W73: =IF(G73="","",IF(OR(G73="Novo contato",G73="Em conversa"),IF(J73="",TODAY(),J73+1),IF(G73="Avaliação marcada",IF(L73="",TODAY(),L73-1),IF(G73="Proposta enviada",IF(J73="",TODAY(),J73+2),IF(G73="Fechou pacote",IF(J73="",TODAY(),J73+7),IF(G73="Em tratamento",IF(M73="",TODAY(),IF(TODAY()<=M73+1,M73+1,EDATE(M73,6)-30)),IF(G73="Pós-venda",IF(J73="",TODAY(),J73+7),IF(G73="Perdido",IF(J73="",TODAY(),J73+60),"")))))))) -> 46275
A74: Cliente 073 | B74: (15) 99999-8395 | C74: Instagram (anúncio) | E74: Criolipólise | F74: =IF(OR(E74="",E74="A completar",E74="Ainda não sabe"),"",IF(OR(E74="Limpeza de pele",E74="Peeling de diamante",E74="Microagulhamento"),"Rosto","Corpo")) -> Corpo | G74: Novo contato | I74: Nina | J74: 46291 | K74: 0 | P74: =IF(M74="","",EDATE(M74,6)) | Q74: =IF(W74="","",IF(WEEKDAY(W74)=1,W74+1,W74)) -> 46293 | R74: =IF(Q74="","",IF(AND(N(K74)>=3,G74<>"Perdido"),"Mover para Perdido",IF(Q74<TODAY(),"Atrasado",IF(Q74=TODAY(),"Hoje","No prazo")))) -> Atrasado | V74: (em branco) | W74: =IF(G74="","",IF(OR(G74="Novo contato",G74="Em conversa"),IF(J74="",TODAY(),J74+1),IF(G74="Avaliação marcada",IF(L74="",TODAY(),L74-1),IF(G74="Proposta enviada",IF(J74="",TODAY(),J74+2),IF(G74="Fechou pacote",IF(J74="",TODAY(),J74+7),IF(G74="Em tratamento",IF(M74="",TODAY(),IF(TODAY()<=M74+1,M74+1,EDATE(M74,6)-30)),IF(G74="Pós-venda",IF(J74="",TODAY(),J74+7),IF(G74="Perdido",IF(J74="",TODAY(),J74+60),"")))))))) -> 46292
A75: Cliente 074 | B75: (15) 99999-0440 | C75: Indicação | E75: Microagulhamento | F75: =IF(OR(E75="",E75="A completar",E75="Ainda não sabe"),"",IF(OR(E75="Limpeza de pele",E75="Peeling de diamante",E75="Microagulhamento"),"Rosto","Corpo")) -> Rosto | G75: Em conversa | I75: Nina | J75: 46294 | K75: 0 | P75: =IF(M75="","",EDATE(M75,6)) | Q75: =IF(W75="","",IF(WEEKDAY(W75)=1,W75+1,W75)) -> 46295 | R75: =IF(Q75="","",IF(AND(N(K75)>=3,G75<>"Perdido"),"Mover para Perdido",IF(Q75<TODAY(),"Atrasado",IF(Q75=TODAY(),"Hoje","No prazo")))) -> Atrasado | S75: Já fez em outra clínica | V75: pediu preço | W75: =IF(G75="","",IF(OR(G75="Novo contato",G75="Em conversa"),IF(J75="",TODAY(),J75+1),IF(G75="Avaliação marcada",IF(L75="",TODAY(),L75-1),IF(G75="Proposta enviada",IF(J75="",TODAY(),J75+2),IF(G75="Fechou pacote",IF(J75="",TODAY(),J75+7),IF(G75="Em tratamento",IF(M75="",TODAY(),IF(TODAY()<=M75+1,M75+1,EDATE(M75,6)-30)),IF(G75="Pós-venda",IF(J75="",TODAY(),J75+7),IF(G75="Perdido",IF(J75="",TODAY(),J75+60),"")))))))) -> 46295
A76: Cliente 075 | B76: (15) 99999-0698 | C76: Google | E76: Depilação a laser | F76: =IF(OR(E76="",E76="A completar",E76="Ainda não sabe"),"",IF(OR(E76="Limpeza de pele",E76="Peeling de diamante",E76="Microagulhamento"),"Rosto","Corpo")) -> Corpo | G76: Avaliação marcada | I76: Nina | J76: 46257 | K76: 0 | P76: =IF(M76="","",EDATE(M76,6)) | Q76: =IF(W76="","",IF(WEEKDAY(W76)=1,W76+1,W76)) -> 46309 | R76: =IF(Q76="","",IF(AND(N(K76)>=3,G76<>"Perdido"),"Mover para Perdido",IF(Q76<TODAY(),"Atrasado",IF(Q76=TODAY(),"Hoje","No prazo")))) -> Hoje | S76: Já fez em outra clínica | V76: remarcar | W76: =IF(G76="","",IF(OR(G76="Novo contato",G76="Em conversa"),IF(J76="",TODAY(),J76+1),IF(G76="Avaliação marcada",IF(L76="",TODAY(),L76-1),IF(G76="Proposta enviada",IF(J76="",TODAY(),J76+2),IF(G76="Fechou pacote",IF(J76="",TODAY(),J76+7),IF(G76="Em tratamento",IF(M76="",TODAY(),IF(TODAY()<=M76+1,M76+1,EDATE(M76,6)-30)),IF(G76="Pós-venda",IF(J76="",TODAY(),J76+7),IF(G76="Perdido",IF(J76="",TODAY(),J76+60),"")))))))) -> 46309
A77: Cliente 076 | B77: (15) 99999-2618 | C77: Instagram (anúncio) | E77: Depilação a laser | F77: =IF(OR(E77="",E77="A completar",E77="Ainda não sabe"),"",IF(OR(E77="Limpeza de pele",E77="Peeling de diamante",E77="Microagulhamento"),"Rosto","Corpo")) -> Corpo | G77: Em conversa | I77: Nina | J77: 46274 | K77: 1 | P77: =IF(M77="","",EDATE(M77,6)) | Q77: =IF(W77="","",IF(WEEKDAY(W77)=1,W77+1,W77)) -> 46275 | R77: =IF(Q77="","",IF(AND(N(K77)>=3,G77<>"Perdido"),"Mover para Perdido",IF(Q77<TODAY(),"Atrasado",IF(Q77=TODAY(),"Hoje","No prazo")))) -> Atrasado | S77: Prefere áudio | V77: sumiu | W77: =IF(G77="","",IF(OR(G77="Novo contato",G77="Em conversa"),IF(J77="",TODAY(),J77+1),IF(G77="Avaliação marcada",IF(L77="",TODAY(),L77-1),IF(G77="Proposta enviada",IF(J77="",TODAY(),J77+2),IF(G77="Fechou pacote",IF(J77="",TODAY(),J77+7),IF(G77="Em tratamento",IF(M77="",TODAY(),IF(TODAY()<=M77+1,M77+1,EDATE(M77,6)-30)),IF(G77="Pós-venda",IF(J77="",TODAY(),J77+7),IF(G77="Perdido",IF(J77="",TODAY(),J77+60),"")))))))) -> 46275
A78: Cliente 077 | B78: (15) 99999-6600 | C78: Indicação | E78: Depilação a laser | F78: =IF(OR(E78="",E78="A completar",E78="Ainda não sabe"),"",IF(OR(E78="Limpeza de pele",E78="Peeling de diamante",E78="Microagulhamento"),"Rosto","Corpo")) -> Corpo | G78: Em conversa | I78: Nina | K78: 0 | P78: =IF(M78="","",EDATE(M78,6)) | Q78: =IF(W78="","",IF(WEEKDAY(W78)=1,W78+1,W78)) -> 46309 | R78: =IF(Q78="","",IF(AND(N(K78)>=3,G78<>"Perdido"),"Mover para Perdido",IF(Q78<TODAY(),"Atrasado",IF(Q78=TODAY(),"Hoje","No prazo")))) -> Hoje | S78: Perguntou do resultado: nunca prometer cm ou kg | V78: ligar de novo | W78: =IF(G78="","",IF(OR(G78="Novo contato",G78="Em conversa"),IF(J78="",TODAY(),J78+1),IF(G78="Avaliação marcada",IF(L78="",TODAY(),L78-1),IF(G78="Proposta enviada",IF(J78="",TODAY(),J78+2),IF(G78="Fechou pacote",IF(J78="",TODAY(),J78+7),IF(G78="Em tratamento",IF(M78="",TODAY(),IF(TODAY()<=M78+1,M78+1,EDATE(M78,6)-30)),IF(G78="Pós-venda",IF(J78="",TODAY(),J78+7),IF(G78="Perdido",IF(J78="",TODAY(),J78+60),"")))))))) -> 46309
A79: Cliente 078 | B79: (15) 99999-0272 | C79: Instagram (anúncio) | E79: Microagulhamento | F79: =IF(OR(E79="",E79="A completar",E79="Ainda não sabe"),"",IF(OR(E79="Limpeza de pele",E79="Peeling de diamante",E79="Microagulhamento"),"Rosto","Corpo")) -> Rosto | G79: Em conversa | I79: Nina | K79: 1 | P79: =IF(M79="","",EDATE(M79,6)) | Q79: =IF(W79="","",IF(WEEKDAY(W79)=1,W79+1,W79)) -> 46309 | R79: =IF(Q79="","",IF(AND(N(K79)>=3,G79<>"Perdido"),"Mover para Perdido",IF(Q79<TODAY(),"Atrasado",IF(Q79=TODAY(),"Hoje","No prazo")))) -> Hoje | S79: Pediu foto de antes e depois: só com autorização escrita | V79: sumiu | W79: =IF(G79="","",IF(OR(G79="Novo contato",G79="Em conversa"),IF(J79="",TODAY(),J79+1),IF(G79="Avaliação marcada",IF(L79="",TODAY(),L79-1),IF(G79="Proposta enviada",IF(J79="",TODAY(),J79+2),IF(G79="Fechou pacote",IF(J79="",TODAY(),J79+7),IF(G79="Em tratamento",IF(M79="",TODAY(),IF(TODAY()<=M79+1,M79+1,EDATE(M79,6)-30)),IF(G79="Pós-venda",IF(J79="",TODAY(),J79+7),IF(G79="Perdido",IF(J79="",TODAY(),J79+60),"")))))))) -> 46309
A80: Cliente 079 | B80: (15) 99999-7427 | C80: Instagram | E80: A completar | F80: =IF(OR(E80="",E80="A completar",E80="Ainda não sabe"),"",IF(OR(E80="Limpeza de pele",E80="Peeling de diamante",E80="Microagulhamento"),"Rosto","Corpo")) | G80: Em conversa | I80: Nina | J80: 46239 | K80: 1 | P80: =IF(M80="","",EDATE(M80,6)) | Q80: =IF(W80="","",IF(WEEKDAY(W80)=1,W80+1,W80)) -> 46240 | R80: =IF(Q80="","",IF(AND(N(K80)>=3,G80<>"Perdido"),"Mover para Perdido",IF(Q80<TODAY(),"Atrasado",IF(Q80=TODAY(),"Hoje","No prazo")))) -> Atrasado | S80: Prefere áudio | V80: não respondeu | W80: =IF(G80="","",IF(OR(G80="Novo contato",G80="Em conversa"),IF(J80="",TODAY(),J80+1),IF(G80="Avaliação marcada",IF(L80="",TODAY(),L80-1),IF(G80="Proposta enviada",IF(J80="",TODAY(),J80+2),IF(G80="Fechou pacote",IF(J80="",TODAY(),J80+7),IF(G80="Em tratamento",IF(M80="",TODAY(),IF(TODAY()<=M80+1,M80+1,EDATE(M80,6)-30)),IF(G80="Pós-venda",IF(J80="",TODAY(),J80+7),IF(G80="Perdido",IF(J80="",TODAY(),J80+60),"")))))))) -> 46240
A81: Cliente 080 | B81: (15) 99999-8760 | C81: Instagram | E81: Drenagem linfática | F81: =IF(OR(E81="",E81="A completar",E81="Ainda não sabe"),"",IF(OR(E81="Limpeza de pele",E81="Peeling de diamante",E81="Microagulhamento"),"Rosto","Corpo")) -> Corpo | G81: Avaliação marcada | I81: Nina | J81: 46303 | K81: 0 | P81: =IF(M81="","",EDATE(M81,6)) | Q81: =IF(W81="","",IF(WEEKDAY(W81)=1,W81+1,W81)) -> 46309 | R81: =IF(Q81="","",IF(AND(N(K81)>=3,G81<>"Perdido"),"Mover para Perdido",IF(Q81<TODAY(),"Atrasado",IF(Q81=TODAY(),"Hoje","No prazo")))) -> Hoje | S81: Já fez em outra clínica | V81: remarcar | W81: =IF(G81="","",IF(OR(G81="Novo contato",G81="Em conversa"),IF(J81="",TODAY(),J81+1),IF(G81="Avaliação marcada",IF(L81="",TODAY(),L81-1),IF(G81="Proposta enviada",IF(J81="",TODAY(),J81+2),IF(G81="Fechou pacote",IF(J81="",TODAY(),J81+7),IF(G81="Em tratamento",IF(M81="",TODAY(),IF(TODAY()<=M81+1,M81+1,EDATE(M81,6)-30)),IF(G81="Pós-venda",IF(J81="",TODAY(),J81+7),IF(G81="Perdido",IF(J81="",TODAY(),J81+60),"")))))))) -> 46309
F82: =IF(OR(E82="",E82="A completar",E82="Ainda não sabe"),"",IF(OR(E82="Limpeza de pele",E82="Peeling de diamante",E82="Microagulhamento"),"Rosto","Corpo")) | P82: =IF(M82="","",EDATE(M82,6)) | Q82: =IF(W82="","",IF(WEEKDAY(W82)=1,W82+1,W82)) | R82: =IF(Q82="","",IF(AND(N(K82)>=3,G82<>"Perdido"),"Mover para Perdido",IF(Q82<TODAY(),"Atrasado",IF(Q82=TODAY(),"Hoje","No prazo")))) | W82: =IF(G82="","",IF(OR(G82="Novo contato",G82="Em conversa"),IF(J82="",TODAY(),J82+1),IF(G82="Avaliação marcada",IF(L82="",TODAY(),L82-1),IF(G82="Proposta enviada",IF(J82="",TODAY(),J82+2),IF(G82="Fechou pacote",IF(J82="",TODAY(),J82+7),IF(G82="Em tratamento",IF(M82="",TODAY(),IF(TODAY()<=M82+1,M82+1,EDATE(M82,6)-30)),IF(G82="Pós-venda",IF(J82="",TODAY(),J82+7),IF(G82="Perdido",IF(J82="",TODAY(),J82+60),""))))))))
F83: =IF(OR(E83="",E83="A completar",E83="Ainda não sabe"),"",IF(OR(E83="Limpeza de pele",E83="Peeling de diamante",E83="Microagulhamento"),"Rosto","Corpo")) | P83: =IF(M83="","",EDATE(M83,6)) | Q83: =IF(W83="","",IF(WEEKDAY(W83)=1,W83+1,W83)) | R83: =IF(Q83="","",IF(AND(N(K83)>=3,G83<>"Perdido"),"Mover para Perdido",IF(Q83<TODAY(),"Atrasado",IF(Q83=TODAY(),"Hoje","No prazo")))) | W83: =IF(G83="","",IF(OR(G83="Novo contato",G83="Em conversa"),IF(J83="",TODAY(),J83+1),IF(G83="Avaliação marcada",IF(L83="",TODAY(),L83-1),IF(G83="Proposta enviada",IF(J83="",TODAY(),J83+2),IF(G83="Fechou pacote",IF(J83="",TODAY(),J83+7),IF(G83="Em tratamento",IF(M83="",TODAY(),IF(TODAY()<=M83+1,M83+1,EDATE(M83,6)-30)),IF(G83="Pós-venda",IF(J83="",TODAY(),J83+7),IF(G83="Perdido",IF(J83="",TODAY(),J83+60),""))))))))
F84: =IF(OR(E84="",E84="A completar",E84="Ainda não sabe"),"",IF(OR(E84="Limpeza de pele",E84="Peeling de diamante",E84="Microagulhamento"),"Rosto","Corpo")) | P84: =IF(M84="","",EDATE(M84,6)) | Q84: =IF(W84="","",IF(WEEKDAY(W84)=1,W84+1,W84)) | R84: =IF(Q84="","",IF(AND(N(K84)>=3,G84<>"Perdido"),"Mover para Perdido",IF(Q84<TODAY(),"Atrasado",IF(Q84=TODAY(),"Hoje","No prazo")))) | W84: =IF(G84="","",IF(OR(G84="Novo contato",G84="Em conversa"),IF(J84="",TODAY(),J84+1),IF(G84="Avaliação marcada",IF(L84="",TODAY(),L84-1),IF(G84="Proposta enviada",IF(J84="",TODAY(),J84+2),IF(G84="Fechou pacote",IF(J84="",TODAY(),J84+7),IF(G84="Em tratamento",IF(M84="",TODAY(),IF(TODAY()<=M84+1,M84+1,EDATE(M84,6)-30)),IF(G84="Pós-venda",IF(J84="",TODAY(),J84+7),IF(G84="Perdido",IF(J84="",TODAY(),J84+60),""))))))))
F85: =IF(OR(E85="",E85="A completar",E85="Ainda não sabe"),"",IF(OR(E85="Limpeza de pele",E85="Peeling de diamante",E85="Microagulhamento"),"Rosto","Corpo")) | P85: =IF(M85="","",EDATE(M85,6)) | Q85: =IF(W85="","",IF(WEEKDAY(W85)=1,W85+1,W85)) | R85: =IF(Q85="","",IF(AND(N(K85)>=3,G85<>"Perdido"),"Mover para Perdido",IF(Q85<TODAY(),"Atrasado",IF(Q85=TODAY(),"Hoje","No prazo")))) | W85: =IF(G85="","",IF(OR(G85="Novo contato",G85="Em conversa"),IF(J85="",TODAY(),J85+1),IF(G85="Avaliação marcada",IF(L85="",TODAY(),L85-1),IF(G85="Proposta enviada",IF(J85="",TODAY(),J85+2),IF(G85="Fechou pacote",IF(J85="",TODAY(),J85+7),IF(G85="Em tratamento",IF(M85="",TODAY(),IF(TODAY()<=M85+1,M85+1,EDATE(M85,6)-30)),IF(G85="Pós-venda",IF(J85="",TODAY(),J85+7),IF(G85="Perdido",IF(J85="",TODAY(),J85+60),""))))))))
F86: =IF(OR(E86="",E86="A completar",E86="Ainda não sabe"),"",IF(OR(E86="Limpeza de pele",E86="Peeling de diamante",E86="Microagulhamento"),"Rosto","Corpo")) | P86: =IF(M86="","",EDATE(M86,6)) | Q86: =IF(W86="","",IF(WEEKDAY(W86)=1,W86+1,W86)) | R86: =IF(Q86="","",IF(AND(N(K86)>=3,G86<>"Perdido"),"Mover para Perdido",IF(Q86<TODAY(),"Atrasado",IF(Q86=TODAY(),"Hoje","No prazo")))) | W86: =IF(G86="","",IF(OR(G86="Novo contato",G86="Em conversa"),IF(J86="",TODAY(),J86+1),IF(G86="Avaliação marcada",IF(L86="",TODAY(),L86-1),IF(G86="Proposta enviada",IF(J86="",TODAY(),J86+2),IF(G86="Fechou pacote",IF(J86="",TODAY(),J86+7),IF(G86="Em tratamento",IF(M86="",TODAY(),IF(TODAY()<=M86+1,M86+1,EDATE(M86,6)-30)),IF(G86="Pós-venda",IF(J86="",TODAY(),J86+7),IF(G86="Perdido",IF(J86="",TODAY(),J86+60),""))))))))
F87: =IF(OR(E87="",E87="A completar",E87="Ainda não sabe"),"",IF(OR(E87="Limpeza de pele",E87="Peeling de diamante",E87="Microagulhamento"),"Rosto","Corpo")) | P87: =IF(M87="","",EDATE(M87,6)) | Q87: =IF(W87="","",IF(WEEKDAY(W87)=1,W87+1,W87)) | R87: =IF(Q87="","",IF(AND(N(K87)>=3,G87<>"Perdido"),"Mover para Perdido",IF(Q87<TODAY(),"Atrasado",IF(Q87=TODAY(),"Hoje","No prazo")))) | W87: =IF(G87="","",IF(OR(G87="Novo contato",G87="Em conversa"),IF(J87="",TODAY(),J87+1),IF(G87="Avaliação marcada",IF(L87="",TODAY(),L87-1),IF(G87="Proposta enviada",IF(J87="",TODAY(),J87+2),IF(G87="Fechou pacote",IF(J87="",TODAY(),J87+7),IF(G87="Em tratamento",IF(M87="",TODAY(),IF(TODAY()<=M87+1,M87+1,EDATE(M87,6)-30)),IF(G87="Pós-venda",IF(J87="",TODAY(),J87+7),IF(G87="Perdido",IF(J87="",TODAY(),J87+60),""))))))))
F88: =IF(OR(E88="",E88="A completar",E88="Ainda não sabe"),"",IF(OR(E88="Limpeza de pele",E88="Peeling de diamante",E88="Microagulhamento"),"Rosto","Corpo")) | P88: =IF(M88="","",EDATE(M88,6)) | Q88: =IF(W88="","",IF(WEEKDAY(W88)=1,W88+1,W88)) | R88: =IF(Q88="","",IF(AND(N(K88)>=3,G88<>"Perdido"),"Mover para Perdido",IF(Q88<TODAY(),"Atrasado",IF(Q88=TODAY(),"Hoje","No prazo")))) | W88: =IF(G88="","",IF(OR(G88="Novo contato",G88="Em conversa"),IF(J88="",TODAY(),J88+1),IF(G88="Avaliação marcada",IF(L88="",TODAY(),L88-1),IF(G88="Proposta enviada",IF(J88="",TODAY(),J88+2),IF(G88="Fechou pacote",IF(J88="",TODAY(),J88+7),IF(G88="Em tratamento",IF(M88="",TODAY(),IF(TODAY()<=M88+1,M88+1,EDATE(M88,6)-30)),IF(G88="Pós-venda",IF(J88="",TODAY(),J88+7),IF(G88="Perdido",IF(J88="",TODAY(),J88+60),""))))))))
F89: =IF(OR(E89="",E89="A completar",E89="Ainda não sabe"),"",IF(OR(E89="Limpeza de pele",E89="Peeling de diamante",E89="Microagulhamento"),"Rosto","Corpo")) | P89: =IF(M89="","",EDATE(M89,6)) | Q89: =IF(W89="","",IF(WEEKDAY(W89)=1,W89+1,W89)) | R89: =IF(Q89="","",IF(AND(N(K89)>=3,G89<>"Perdido"),"Mover para Perdido",IF(Q89<TODAY(),"Atrasado",IF(Q89=TODAY(),"Hoje","No prazo")))) | W89: =IF(G89="","",IF(OR(G89="Novo contato",G89="Em conversa"),IF(J89="",TODAY(),J89+1),IF(G89="Avaliação marcada",IF(L89="",TODAY(),L89-1),IF(G89="Proposta enviada",IF(J89="",TODAY(),J89+2),IF(G89="Fechou pacote",IF(J89="",TODAY(),J89+7),IF(G89="Em tratamento",IF(M89="",TODAY(),IF(TODAY()<=M89+1,M89+1,EDATE(M89,6)-30)),IF(G89="Pós-venda",IF(J89="",TODAY(),J89+7),IF(G89="Perdido",IF(J89="",TODAY(),J89+60),""))))))))
F90: =IF(OR(E90="",E90="A completar",E90="Ainda não sabe"),"",IF(OR(E90="Limpeza de pele",E90="Peeling de diamante",E90="Microagulhamento"),"Rosto","Corpo")) | P90: =IF(M90="","",EDATE(M90,6)) | Q90: =IF(W90="","",IF(WEEKDAY(W90)=1,W90+1,W90)) | R90: =IF(Q90="","",IF(AND(N(K90)>=3,G90<>"Perdido"),"Mover para Perdido",IF(Q90<TODAY(),"Atrasado",IF(Q90=TODAY(),"Hoje","No prazo")))) | W90: =IF(G90="","",IF(OR(G90="Novo contato",G90="Em conversa"),IF(J90="",TODAY(),J90+1),IF(G90="Avaliação marcada",IF(L90="",TODAY(),L90-1),IF(G90="Proposta enviada",IF(J90="",TODAY(),J90+2),IF(G90="Fechou pacote",IF(J90="",TODAY(),J90+7),IF(G90="Em tratamento",IF(M90="",TODAY(),IF(TODAY()<=M90+1,M90+1,EDATE(M90,6)-30)),IF(G90="Pós-venda",IF(J90="",TODAY(),J90+7),IF(G90="Perdido",IF(J90="",TODAY(),J90+60),""))))))))
F91: =IF(OR(E91="",E91="A completar",E91="Ainda não sabe"),"",IF(OR(E91="Limpeza de pele",E91="Peeling de diamante",E91="Microagulhamento"),"Rosto","Corpo")) | P91: =IF(M91="","",EDATE(M91,6)) | Q91: =IF(W91="","",IF(WEEKDAY(W91)=1,W91+1,W91)) | R91: =IF(Q91="","",IF(AND(N(K91)>=3,G91<>"Perdido"),"Mover para Perdido",IF(Q91<TODAY(),"Atrasado",IF(Q91=TODAY(),"Hoje","No prazo")))) | W91: =IF(G91="","",IF(OR(G91="Novo contato",G91="Em conversa"),IF(J91="",TODAY(),J91+1),IF(G91="Avaliação marcada",IF(L91="",TODAY(),L91-1),IF(G91="Proposta enviada",IF(J91="",TODAY(),J91+2),IF(G91="Fechou pacote",IF(J91="",TODAY(),J91+7),IF(G91="Em tratamento",IF(M91="",TODAY(),IF(TODAY()<=M91+1,M91+1,EDATE(M91,6)-30)),IF(G91="Pós-venda",IF(J91="",TODAY(),J91+7),IF(G91="Perdido",IF(J91="",TODAY(),J91+60),""))))))))
F92: =IF(OR(E92="",E92="A completar",E92="Ainda não sabe"),"",IF(OR(E92="Limpeza de pele",E92="Peeling de diamante",E92="Microagulhamento"),"Rosto","Corpo")) | P92: =IF(M92="","",EDATE(M92,6)) | Q92: =IF(W92="","",IF(WEEKDAY(W92)=1,W92+1,W92)) | R92: =IF(Q92="","",IF(AND(N(K92)>=3,G92<>"Perdido"),"Mover para Perdido",IF(Q92<TODAY(),"Atrasado",IF(Q92=TODAY(),"Hoje","No prazo")))) | W92: =IF(G92="","",IF(OR(G92="Novo contato",G92="Em conversa"),IF(J92="",TODAY(),J92+1),IF(G92="Avaliação marcada",IF(L92="",TODAY(),L92-1),IF(G92="Proposta enviada",IF(J92="",TODAY(),J92+2),IF(G92="Fechou pacote",IF(J92="",TODAY(),J92+7),IF(G92="Em tratamento",IF(M92="",TODAY(),IF(TODAY()<=M92+1,M92+1,EDATE(M92,6)-30)),IF(G92="Pós-venda",IF(J92="",TODAY(),J92+7),IF(G92="Perdido",IF(J92="",TODAY(),J92+60),""))))))))
F93: =IF(OR(E93="",E93="A completar",E93="Ainda não sabe"),"",IF(OR(E93="Limpeza de pele",E93="Peeling de diamante",E93="Microagulhamento"),"Rosto","Corpo")) | P93: =IF(M93="","",EDATE(M93,6)) | Q93: =IF(W93="","",IF(WEEKDAY(W93)=1,W93+1,W93)) | R93: =IF(Q93="","",IF(AND(N(K93)>=3,G93<>"Perdido"),"Mover para Perdido",IF(Q93<TODAY(),"Atrasado",IF(Q93=TODAY(),"Hoje","No prazo")))) | W93: =IF(G93="","",IF(OR(G93="Novo contato",G93="Em conversa"),IF(J93="",TODAY(),J93+1),IF(G93="Avaliação marcada",IF(L93="",TODAY(),L93-1),IF(G93="Proposta enviada",IF(J93="",TODAY(),J93+2),IF(G93="Fechou pacote",IF(J93="",TODAY(),J93+7),IF(G93="Em tratamento",IF(M93="",TODAY(),IF(TODAY()<=M93+1,M93+1,EDATE(M93,6)-30)),IF(G93="Pós-venda",IF(J93="",TODAY(),J93+7),IF(G93="Perdido",IF(J93="",TODAY(),J93+60),""))))))))
... F500: =IF(OR(E500="",E500="A completar",E500="Ainda não sabe"),"",IF(OR(E500="Limpeza de pele",E500="Peeling de diamante",E500="Microagulhamento"),"Rosto","Corpo")) | P500: =IF(M500="","",EDATE(M500,6)) | Q500: =IF(W500="","",IF(WEEKDAY(W500)=1,W500+1,W500)) | R500: =IF(Q500="","",IF(AND(N(K500)>=3,G500<>"Perdido"),"Mover para Perdido",IF(Q500<TODAY(),"Atrasado",IF(Q500=TODAY(),"Hoje","No prazo")))) | W500: =IF(G500="","",IF(OR(G500="Novo contato",G500="Em conversa"),IF(J500="",TODAY(),J500+1),IF(G500="Avaliação marcada",IF(L500="",TODAY(),L500-1),IF(G500="Proposta enviada",IF(J500="",TODAY(),J500+2),IF(G500="Fechou pacote",IF(J500="",TODAY(),J500+7),IF(G500="Em tratamento",IF(M500="",TODAY(),IF(TODAY()<=M500+1,M500+1,EDATE(M500,6)-30)),IF(G500="Pós-venda",IF(J500="",TODAY(),J500+7),IF(G500="Perdido",IF(J500="",TODAY(),J500+60),""))))))))

Sheet Etapas do funil
A1: Etapas do funil
A2: As colunas do quadro, na ordem do caminho da cliente.
A4: # | B4: Etapa | C4: Quando o cartão entra aqui | D4: Quem move para a próxima | E4: Situações da planilha antiga que vieram para cá
A5: 1 | B5: Novo contato | C5: A cliente mandou a primeira mensagem (WhatsApp, Instagram, Google, indicação, fachada). | D5: Nina | E5: (em branco)
A6: 2 | B6: Em conversa | C6: A Nina já respondeu, a cliente pediu preço ou tirou dúvida, mas ainda não marcou a avaliação. | D6: Nina | E6: pediu preço · ligar de novo · não respondeu · sumiu
A7: 3 | B7: Avaliação marcada | C7: A avaliação gratuita está com dia e hora marcados. | D7: Nina ou Otávio | E7: marcou avaliação · remarcar · avaliação?
A8: 4 | B8: Proposta enviada | C8: A cliente fez a avaliação, o Otávio montou a proposta e a Nina enviou no mesmo dia. | D8: Nina | E8: fez avaliação · achou caro · vai pensar
A9: 5 | B9: Fechou pacote | C9: A cliente pagou o pacote e falta fazer a 1ª sessão. | D9: Quem registrar a 1ª sessão | E9: fechou pacote
A10: 6 | B10: Em tratamento | C10: A 1ª sessão foi feita. A planilha mostra a validade do pacote. | D10: Quem registrar a última sessão
A11: 7 | B11: Pós-venda | C11: O pacote terminou. Pedir opinião e indicação e oferecer o próximo tratamento. | D11: Nina
A12: — | B12: Perdido | C12: A cliente disse não ou não respondeu depois de 3 tentativas. Escolher o motivo é obrigatório. Pode voltar para Em conversa se a cliente reaparecer. | D12: Nina
B13: REGRA | C13: O cartão não vai para Fechou pacote sem a avaliação feita. A clínica só vende pacote depois da avaliação.

Sheet Dados do cliente
A1: Dados de cada cliente
A2: O que cada coluna da aba Clientes significa. ★ = obrigatório.
A4: Campo | B4: Grupo | C4: Como preenche | D4: Observação
A5: Nome ★ | B5: Identificação | C5: Texto
A6: Telefone / WhatsApp ★ | B6: Identificação | C6: Número com DDD | D6: Confira se a cliente já não está cadastrada.
A7: Origem ★ | B7: De onde veio | C7: Menu | D7: Instagram · Instagram (anúncio) · Google · Indicação · Fachada · Outro
A8: Indicada por | B8: De onde veio | C8: Texto | D8: Só quando a origem é Indicação.
A9: Interesse ★ | B9: De onde veio | C9: Menu | D9: Tratamentos da tabela de preços ou "Ainda não sabe".
A10: Área | B10: De onde veio | C10: Automático | D10: Rosto ou Corpo, a partir do interesse.
A11: Etapa ★ | B11: Andamento | C11: Menu | D11: A coluna do quadro em que a cliente está.
A12: Etiqueta da proposta | B12: Andamento | C12: Menu | D12: achou caro · vai pensar · quer parcelar. Só na etapa Proposta enviada.
A13: Responsável ★ | B13: Andamento | C13: Menu | D13: Nina por padrão.
A14: Último contato ★ | B14: Andamento | C14: Data | D14: Atualize sempre que falar com a cliente.
A15: Tentativas sem resposta | B15: Andamento | C15: Número de 0 a 3 | D15: Volta para 0 quando a cliente responde.
A16: Data da avaliação | B16: Avaliação | C16: Data | D16: Dia marcado da avaliação gratuita.
A17: Data da 1ª sessão | B17: Pacote | C17: Data | D17: Começa a contar a validade de 6 meses.
... A26: Ainda não estão na planilha | B26: Próxima versão | C26: — | D26: Valor da proposta, forma de pagamento, data de envio da proposta, profissional, autorização de foto (sim/não e data) e exceção aprovada pela Paula. Estão descritos no documento do produto.

Sheet Regras de retorno
A1: Regras de retorno
A2: Quando a Nina volta a falar com a cliente.
A4: Situação | B4: Quando | C4: De onde vem a regra | D4: A planilha calcula sozinha?
A5: Contato novo parou de responder | B5: 1 dia depois do último contato | C5: Roteiro do WhatsApp | D5: Sim
A6: Fez a avaliação e não respondeu à proposta | B6: 2 dias depois do último contato | C6: Roteiro do WhatsApp | D6: Sim
A7: Comprou o pacote | B7: Pós-venda 7 dias depois | C7: Roteiro do WhatsApp | D7: Sim
A8: Contato sem data | B8: No mesmo dia | C8: Roteiro do WhatsApp | D8: Sim
A9: Fez a 1ª sessão | B9: 1 dia depois da 1ª sessão | C9: Oferta e preços (prazo sugerido) | D9: Sim
A10: Fez criolipólise | B10: Marcar retorno com o Otávio aos 53 dias (consulta aos 60 dias) | C10: Oferta e preços | D10: Não: anotar na observação
A11: Cliente não responde | B11: Até 3 tentativas. Na 3ª, mover para Perdido | C11: Definido neste projeto | D11: Sim (avisa)
A12: Contato perdido | B12: Uma nova tentativa 60 dias depois | C12: Sugestão | D12: Sim
A13: Avaliação marcada | B13: Lembrete na véspera | C13: Sugestão | D13: Sim
A14: Faltou ou pediu para remarcar a avaliação | B14: No mesmo dia | C14: Sugestão | D14: Sim (quando não há data de avaliação)
A15: Etiqueta achou caro ou vai pensar | B15: 2 dias. Lembrar: 6x sem juros ou 10% à vista no Pix | C15: Oferta e preços | D15: Sim
... A19: Horário | B19: Seg a sex, 9h às 19h · sáb, 9h às 13h. Domingo passa para segunda | C19: Oferta e preços | D19: Sim (domingo)

Sheet Regras da clínica
A1: Regras que ninguém quebra
A2: E o que o CRM faz para proteger cada uma.
A4: Regra | B4: O que o CRM faz
A5: Só vende pacote depois da avaliação. | B5: O cartão não vai para Fechou pacote sem avaliação feita.
A6: Desconto máximo de 10%, só à vista no Pix. | B6: A forma de pagamento só oferece Pix com 10%, débito ou crédito em até 6x.
A7: Nunca prometer resultado em centímetro ou em quilo. | B7: A etiqueta "Perguntou do resultado" traz o lembrete.
A8: Foto de antes e depois só com autorização por escrito. | B8: A etiqueta "Pediu foto de antes e depois" traz o lembrete.
A9: Proposta enviada no mesmo dia da avaliação. | B9: A Nina confere na lista de retornos do dia.
A10: Exceções só com a Paula, sempre por escrito. | B10: Registrar na observação, com a data.

Sheet Quem usa
A1: Quem usa o CRM
A4: Pessoa | B4: Papel na clínica | C4: O que faz no CRM
A5: Nina | B5: Recepção e WhatsApp | C5: Cadastra cada contato, move as clientes de etapa, registra cada conversa, trabalha os retornos do dia e envia as propostas.
A6: Otávio | B6: Biomédico esteta: avaliações, criolipólise e laser | C6: Registra a avaliação feita, o tratamento indicado e a proposta. Acompanha o retorno de 60 dias da criolipólise.
A7: Camila | B7: Terapeuta corporal: drenagem e modeladora | C7: Marca as sessões feitas das clientes em tratamento corporal.
A8: Paula | B8: Fundadora: define preços e exceções | C8: Acompanha o Painel e aprova as exceções, por escrito.

Sheet Pontos a confirmar
A1: Pontos para a Paula confirmar
A2: Regras sugeridas: os documentos da clínica não dizem o prazo.
A4: Pergunta | B4: Sugestão usada na planilha | C4: Resposta da Paula
A5: Retorno depois da 1ª sessão | B5: 1 dia depois
A6: Lembrete na véspera da avaliação | B6: Sim
A7: Nova tentativa com quem foi para Perdido | B7: 60 dias depois, uma única vez
A8: Oferecer o próximo tratamento depois do fim do pacote | B8: 30 dias depois
A9: Otávio e Camila podem mudar a etapa da cliente? | B9: Só registram avaliações e sessões

Sheet Listas
A1: Listas dos menus
A2: Para incluir uma opção nova, escreva no fim da coluna certa.
A4: Etapa | B4: Origem | C4: Interesse | D4: Etiqueta da proposta | E4: Responsável | F4: Motivo da perda | G4: Pagamento
A5: Novo contato | B5: Instagram | C5: Limpeza de pele | D5: achou caro | E5: Nina | F5: Achou caro | G5: Pix à vista (10% de desconto)
A6: Em conversa | B6: Instagram (anúncio) | C6: Peeling de diamante | D6: vai pensar | E6: Otávio | F6: Não respondeu (3 tentativas) | G6: Débito
A7: Avaliação marcada | B7: Google | C7: Microagulhamento | D7: quer parcelar | E7: Camila | F7: Fechou em outra clínica | G7: Crédito em até 6x
A8: Proposta enviada | B8: Indicação | C8: Drenagem linfática | E8: Paula | F8: Horário não serve
A9: Fechou pacote | B9: Fachada | C9: Massagem modeladora | F9: Desistiu do tratamento
A10: Em tratamento | B10: Outro | C10: Criolipólise | F10: Outro
A11: Pós-venda | B11: A completar | C11: Depilação a laser
A12: Perdido | C12: Ainda não sabe
C13: A completar
